{
    "eadheader": {
        "countryencoding": "iso3166-1",
        "dateencoding": "iso8601",
        "langencoding": "iso639-2b",
        "repositoryencoding": "iso15511",
        "eadid": {
            "countrycode": "US",
            "mainagencycode": "US-NNU-TL",
            "value": "aia_048"
        },
        "filedesc": {
            "titlestmt": {
                "titleproper": [
                    {
                        "value": "Guide to the James P. Sullivan Collection\n                    \u003cnum\u003eAIA.048\u003c/num\u003e\n                "
                    }
                ],
                "author": {
                    "value": "Finding aid prepared by Rebecca Altermatt"
                }
            },
            "PublicationStmt": {
                "publisher": {
                    "value": "Tamiment Library / Wagner Archives"
                },
                "address": {
                    "addressline": [
                        "Elmer Holmes Bobst Library",
                        "70 Washington Square South",
                        "New York, NY, 10012",
                        "(212) 998-2630",
                        "tamiment.wagner@nyu.edu"
                    ]
                },
                "date": "06/30/10"
            }
        },
        "profiledesc": {
            "creation": {
                "value": "This finding aid was produced using the Archivists' Toolkit\n                \u003cdate\u003e2012-03-28T16:08-0400\u003c/date\u003e\n            "
            },
            "langusage": {}
        }
    },
    "archdesc": {
        "level": "collection",
        "did": [
            {
                "omitempty": "",
                "repository": {
                    "corpname": {
                        "value": "Tamiment Library / Wagner Archives"
                    }
                },
                "origination": {
                    "label": "creator"
                },
                "unittitle": {
                    "value": "James P. Sullivan Collection"
                },
                "unitdate": {
                    "value": "1905-1908"
                },
                "physdesc": {
                    "extent": [
                        {
                            "value": "0.25 linear feet"
                        },
                        {
                            "value": "(1 CD - 56 digital images from scrapbook)"
                        }
                    ]
                },
                "abstract": {
                    "label": "Abstract",
                    "value": "James P. Sullivan was the third of six children born to Irish immigrants Jeremiah Sullivan, a grocer, and his wife Elizabeth Flynn Sullivan. Young J.P., or Jim, was born on February 28, 1885 and spent his early years in Manhattan where he attended P.S. 14 on East 27th Street and joined the track team of the St. Bartholomew Boys Club and, later, of the 22nd Regiment. By that time, six foot tall Jim could run a mile in 4:50. In September 1905 at the New York Metro Senior American Athletic Union Championships, Sullivan ran the mile in 4:22 creating a new American record. After impressive showings at the Canadian Championships and the New York Athletic Club Games that same month, he became known in the press as “4:22 Jim” and by March 1906 had been selected for the American Olympic team. The collection consists of items from the Sullivan family scrapbook. Included are photographs, newspaper clippings, correspondence and membership cards for the Irish-American Athletic Club."
                },
                "unitid": {
                    "value": "AIA.048"
                },
                "langmaterial": {
                    "language": {
                        "langcode": "eng"
                    }
                }
            }
        ],
        "accessrestrict": {
            "id": "ref60",
            "head": "Access Restrictions",
            "p": {
                "value": "Open for research without restrictions."
            }
        },
        "prefercite": {
            "id": "ref64",
            "head": "Preferred Citation",
            "p": {
                "value": "Published citations should take the following form: \n                \u003clb/\u003e\n                \u003clb/\u003eIdentification of item, date; Collection name; Collection number; box number; folder number; \n                \u003clb/\u003eArchives of Irish America, Tamiment Library/Robert F. Wagner Labor Archives \n                \u003clb/\u003eElmer Holmes Bobst Library \n                \u003clb/\u003e70 Washington Square South \n                \u003clb/\u003eNew York, NY 10012, New York University Libraries."
            }
        },
        "bioghist": {
            "id": "ref66",
            "head": "Historical/Biographical Note",
            "p": {
                "value": "He married Grace Burke in 1913 – the daughter of Irish immigrants, Richard (a broker at the Custom House) and Mary – and they raised two children, Richard and Elise, on his job as a clerk for the Kings County Court, a position he held until 1958. James P. Sullivan died on 9 April 1965 at age 79."
            }
        },
        "scopecontent": {
            "id": "ref65",
            "head": "Scope and Content Note",
            "p": {
                "value": "Images are available for viewing in a Flikr exhibit at http://www.flickr.com/photos/27630285@N07/3240069844/in/set-72157613167342984/. A copy of the images is also available in the Archives on a Cd-Rom."
            }
        },
        "controlaccess": {
            "subject": [
                {
                    "source": "lcsh",
                    "value": "Irish Americans |x Societies, etc."
                },
                {
                    "source": "lcsh",
                    "value": "Olympics."
                }
            ],
            "corpname": {
                "source": "local",
                "value": "Irish American Athletic Club."
            }
        },
        "dsc": {
            "value": "\n            \u003cc01 id=\"ref2\" level=\"series\"\u003e\n                \u003cdid\u003e\n                    \u003cunittitle\u003eInventory\u003c/unittitle\u003e\n                \u003c/did\u003e\n                \u003cc02 id=\"ref3\" level=\"item\"\u003e\n                    \u003cdid\u003e\n                        \u003cunittitle\u003eNewspaper Clipping: 4:22 Sullivan \"One Record by Which Sullivan is Alone\"\u003c/unittitle\u003e\n                        \u003ccontainer id=\"cid19378001\" type=\"CD\" label=\"Mixed materials\"\u003e1\u003c/container\u003e\n                        \u003ccontainer parent=\"cid19378001\" type=\"item\"\u003eaia048_001\u003c/container\u003e\n                        \u003cunitdate\u003ecirca 1905\u003c/unitdate\u003e\n                    \u003c/did\u003e\n                \u003c/c02\u003e\n                \u003cc02 id=\"ref4\" level=\"item\"\u003e\n                    \u003cdid\u003e\n                        \u003cunittitle\u003ePhotograph: J.P. Sullivan, Track Captain 13th Artillery AC\u003c/unittitle\u003e\n                        \u003ccontainer id=\"cid19378002\" type=\"CD\" label=\"Mixed materials\"\u003e1\u003c/container\u003e\n                        \u003ccontainer parent=\"cid19378002\" type=\"item\"\u003eaia048_002\u003c/container\u003e\n                        \u003cunitdate\u003eundated\u003c/unitdate\u003e\n                    \u003c/did\u003e\n                \u003c/c02\u003e\n                \u003cc02 id=\"ref5\" level=\"item\"\u003e\n                    \u003cdid\u003e\n                        \u003cunittitle\u003e1900 Census - 12th Census of the United States, New York County: Page with Sullivan Family information\u003c/unittitle\u003e\n                        \u003ccontainer id=\"cid19378003\" type=\"CD\" label=\"Mixed materials\"\u003e1\u003c/container\u003e\n                        \u003ccontainer parent=\"cid19378003\" type=\"item\"\u003eaia048_003\u003c/container\u003e\n                        \u003cunitdate\u003e1900\u003c/unitdate\u003e\n                    \u003c/did\u003e\n                \u003c/c02\u003e\n                \u003cc02 id=\"ref6\" level=\"item\"\u003e\n                    \u003cdid\u003e\n                        \u003cunittitle\u003eNewspaper clipping: \"Finish of the One Mile Run J.P. Sullivan 1st, Harvey W. Cohn 2nd\u003c/unittitle\u003e\n                        \u003ccontainer id=\"cid19378004\" type=\"CD\" label=\"Mixed materials\"\u003e1\u003c/container\u003e\n                        \u003ccontainer parent=\"cid19378004\" type=\"item\"\u003eaia048_004\u003c/container\u003e\n                        \u003cunitdate\u003e1905\u003c/unitdate\u003e\n                    \u003c/did\u003e\n                \u003c/c02\u003e\n                \u003cc02 id=\"ref7\" level=\"item\"\u003e\n                    \u003cdid\u003e\n                        \u003cunittitle\u003eLetter from American Committee of the Olympian Games at Athens Greece regarding 1906 games, informing Sullivan he was chosen unanimously to represent the United States; first page only\u003c/unittitle\u003e\n                        \u003ccontainer id=\"cid19378005\" type=\"CD\" label=\"Mixed materials\"\u003e1\u003c/container\u003e\n                        \u003ccontainer parent=\"cid19378005\" type=\"item\"\u003eaia048_005\u003c/container\u003e\n                        \u003cunitdate\u003eMar 8 1906\u003c/unitdate\u003e\n                    \u003c/did\u003e\n                \u003c/c02\u003e\n                \u003cc02 id=\"ref8\" level=\"item\"\u003e\n                    \u003cdid\u003e\n                        \u003cunittitle\u003e1910 Census - 13th Census of the United States, Kings County, Sullivan Family information, 1 page\u003c/unittitle\u003e\n                        \u003ccontainer id=\"cid19378006\" type=\"CD\" label=\"Mixed materials\"\u003e1\u003c/container\u003e\n                        \u003ccontainer parent=\"cid19378006\" type=\"item\"\u003eaia048_006\u003c/container\u003e\n                        \u003cunitdate\u003e1910\u003c/unitdate\u003e\n                    \u003c/did\u003e\n                \u003c/c02\u003e\n                \u003cc02 id=\"ref9\" level=\"item\"\u003e\n                    \u003cdid\u003e\n                        \u003cunittitle\u003ePhotograph: James Sullivan at Acroplis, Athens with two unidentified men\u003c/unittitle\u003e\n                        \u003ccontainer id=\"cid19378007\" type=\"CD\" label=\"Mixed materials\"\u003e1\u003c/container\u003e\n                        \u003ccontainer parent=\"cid19378007\" type=\"item\"\u003eaia048_007\u003c/container\u003e\n                        \u003cunitdate\u003e1906\u003c/unitdate\u003e\n                    \u003c/did\u003e\n                \u003c/c02\u003e\n                \u003cc02 id=\"ref10\" level=\"item\"\u003e\n                    \u003cdid\u003e\n                        \u003cunittitle\u003ePhotograph: James Sullivan at the Porch of the Maidens, the Acroplis, Athens\u003c/unittitle\u003e\n                        \u003ccontainer id=\"cid19378008\" type=\"CD\" label=\"Mixed materials\"\u003e1\u003c/container\u003e\n                        \u003ccontainer parent=\"cid19378008\" type=\"item\"\u003eaia048_008\u003c/container\u003e\n                        \u003cunitdate\u003e1906\u003c/unitdate\u003e\n                    \u003c/did\u003e\n                \u003c/c02\u003e\n                \u003cc02 id=\"ref11\" level=\"item\"\u003e\n                    \u003cdid\u003e\n                        \u003cunittitle\u003eNewpaper clippings: The [Globe and Commercial] Advertiser, New York \"Olympic Stars Peform To-Day at Celtic Park\"\u003c/unittitle\u003e\n                        \u003ccontainer id=\"cid19378009\" type=\"CD\" label=\"Mixed materials\"\u003e1\u003c/container\u003e\n                        \u003ccontainer parent=\"cid19378009\" type=\"item\"\u003eaia048_009\u003c/container\u003e\n                        \u003cunitdate\u003eSep 7, 1908\u003c/unitdate\u003e\n                    \u003c/did\u003e\n                \u003c/c02\u003e\n                \u003cc02 id=\"ref12\" level=\"item\"\u003e\n                    \u003cdid\u003e\n                        \u003cunittitle\u003eCartoon \"Uncle to the Fore!\" by J. Campbell Cory, unidentified publication\u003c/unittitle\u003e\n                        \u003ccontainer id=\"cid19378010\" type=\"CD\" label=\"Mixed materials\"\u003e1\u003c/container\u003e\n                        \u003ccontainer parent=\"cid19378010\" type=\"item\"\u003eaia048_010\u003c/container\u003e\n                        \u003cunitdate\u003eApr 27, 1906 \u003c/unitdate\u003e\n                    \u003c/did\u003e\n                \u003c/c02\u003e\n                \u003cc02 id=\"ref13\" level=\"item\"\u003e\n                    \u003cdid\u003e\n                        \u003cunittitle\u003eCigarette Card: James P. Sullivan, color; Mecca Cigarettes Champion Athlete and Prize Fighter Series\u003c/unittitle\u003e\n                        \u003ccontainer id=\"cid19378011\" type=\"CD\" label=\"Mixed materials\"\u003e1\u003c/container\u003e\n                        \u003ccontainer parent=\"cid19378011\" type=\"item\"\u003eaia048_011\u003c/container\u003e\n                        \u003cunitdate\u003ecirca 1911\u003c/unitdate\u003e\n                    \u003c/did\u003e\n                \u003c/c02\u003e\n                \u003cc02 id=\"ref14\" level=\"item\"\u003e\n                    \u003cdid\u003e\n                        \u003cunittitle\u003eCigarette Card Verso: James P. Sullivan, color; Mecca Cigarettes Champion Athlete and Prize Fighter Series; contains biographical and competition information on Sullivan\u003c/unittitle\u003e\n                        \u003ccontainer id=\"cid19378012\" type=\"CD\" label=\"Mixed materials\"\u003e1\u003c/container\u003e\n                        \u003ccontainer parent=\"cid19378012\" type=\"item\"\u003eaia048_012\u003c/container\u003e\n                        \u003cunitdate\u003ecirca 1911\u003c/unitdate\u003e\n                    \u003c/did\u003e\n                \u003c/c02\u003e\n                \u003cc02 id=\"ref15\" level=\"item\"\u003e\n                    \u003cdid\u003e\n                        \u003cunittitle\u003eNewpaper clipping: \"Irish Heroes of Olympia Honored at Great Feast\", unidentified source\u003c/unittitle\u003e\n                        \u003ccontainer id=\"cid19378013\" type=\"CD\" label=\"Mixed materials\"\u003e1\u003c/container\u003e\n                        \u003ccontainer parent=\"cid19378013\" type=\"item\"\u003eaia048_013\u003c/container\u003e\n                        \u003cunitdate\u003eSep 22, 1908\u003c/unitdate\u003e\n                    \u003c/did\u003e\n                \u003c/c02\u003e\n                \u003cc02 id=\"ref16\" level=\"item\"\u003e\n                    \u003cdid\u003e\n                        \u003cunittitle\u003eMilitary Honorable Discharge document from the State of New York to James Sullivan\u003c/unittitle\u003e\n                        \u003ccontainer id=\"cid19378014\" type=\"CD\" label=\"Mixed materials\"\u003e1\u003c/container\u003e\n                        \u003ccontainer parent=\"cid19378014\" type=\"item\"\u003eaia048_014\u003c/container\u003e\n                        \u003cunitdate\u003eNov 25, 1910\u003c/unitdate\u003e\n                    \u003c/did\u003e\n                \u003c/c02\u003e\n                \u003cc02 id=\"ref17\" level=\"item\"\u003e\n                    \u003cdid\u003e\n                        \u003cunittitle\u003eNewspaper Clipping: \"Marathon Winner Gets Big Welcome\"\u003c/unittitle\u003e\n                        \u003ccontainer id=\"cid19378015\" type=\"CD\" label=\"Mixed materials\"\u003e1\u003c/container\u003e\n                        \u003ccontainer parent=\"cid19378015\" type=\"item\"\u003eaia048_015\u003c/container\u003e\n                        \u003cunitdate\u003eAug 20, 1908\u003c/unitdate\u003e\n                    \u003c/did\u003e\n                \u003c/c02\u003e\n                \u003cc02 id=\"ref18\" level=\"item\"\u003e\n                    \u003cdid\u003e\n                        \u003cunittitle\u003eIrish American Athletic Club Document: \"One Year's Record of the Irish-American Athletic Club\"\u003c/unittitle\u003e\n                        \u003ccontainer id=\"cid19378016\" type=\"CD\" label=\"Mixed materials\"\u003e1\u003c/container\u003e\n                        \u003ccontainer parent=\"cid19378016\" type=\"item\"\u003eaia048_015\u003c/container\u003e\n                        \u003cunitdate\u003ecirca 1905\u003c/unitdate\u003e\n                    \u003c/did\u003e\n                \u003c/c02\u003e\n                \u003cc02 id=\"ref19\" level=\"item\"\u003e\n                    \u003cdid\u003e\n                        \u003cunittitle\u003eIrish American Atheltic Club Document: \"Winners of National Championship at St. Louis Exposition\"\u003c/unittitle\u003e\n                        \u003ccontainer id=\"cid19378017\" type=\"CD\" label=\"Mixed materials\"\u003e1\u003c/container\u003e\n                        \u003ccontainer parent=\"cid19378017\" type=\"item\"\u003eaia048_016\u003c/container\u003e\n                        \u003cunitdate\u003ecirca 1905\u003c/unitdate\u003e\n                    \u003c/did\u003e\n                \u003c/c02\u003e\n                \u003cc02 id=\"ref20\" level=\"item\"\u003e\n                    \u003cdid\u003e\n                        \u003cunittitle\u003eIrish American Athletic Club Photograph: Group\u003c/unittitle\u003e\n                        \u003ccontainer id=\"cid19378018\" type=\"CD\" label=\"Mixed materials\"\u003e1\u003c/container\u003e\n                        \u003ccontainer parent=\"cid19378018\" type=\"item\"\u003eaia048_017\u003c/container\u003e\n                        \u003cunitdate\u003ecirca 1906\u003c/unitdate\u003e\n                    \u003c/did\u003e\n                \u003c/c02\u003e\n                \u003cc02 id=\"ref21\" level=\"item\"\u003e\n                    \u003cdid\u003e\n                        \u003cunittitle\u003eIrish American Athletic Club Membership Card\u003c/unittitle\u003e\n                        \u003ccontainer id=\"cid19378019\" type=\"CD\" label=\"Mixed materials\"\u003e1\u003c/container\u003e\n                        \u003ccontainer parent=\"cid19378019\" type=\"item\"\u003eaia048_019\u003c/container\u003e\n                        \u003cunitdate\u003e1905\u003c/unitdate\u003e\n                    \u003c/did\u003e\n                \u003c/c02\u003e\n                \u003cc02 id=\"ref22\" level=\"item\"\u003e\n                    \u003cdid\u003e\n                        \u003cunittitle\u003eIrish American Athletic Club Membership Card\u003c/unittitle\u003e\n                        \u003ccontainer id=\"cid19378020\" type=\"CD\" label=\"Mixed materials\"\u003e1\u003c/container\u003e\n                        \u003ccontainer parent=\"cid19378020\" type=\"item\"\u003eaia048_020\u003c/container\u003e\n                        \u003cunitdate\u003e1906\u003c/unitdate\u003e\n                    \u003c/did\u003e\n                \u003c/c02\u003e\n                \u003cc02 id=\"ref23\" level=\"item\"\u003e\n                    \u003cdid\u003e\n                        \u003cunittitle\u003eIrish American Athletic Club Membership Card: Verso\u003c/unittitle\u003e\n                        \u003ccontainer id=\"cid19378021\" type=\"CD\" label=\"Mixed materials\"\u003e1\u003c/container\u003e\n                        \u003ccontainer parent=\"cid19378021\" type=\"item\"\u003eaia048_021\u003c/container\u003e\n                        \u003cunitdate\u003e1906\u003c/unitdate\u003e\n                    \u003c/did\u003e\n                \u003c/c02\u003e\n                \u003cc02 id=\"ref24\" level=\"item\"\u003e\n                    \u003cdid\u003e\n                        \u003cunittitle\u003eIrish American Athletic Club Membership Card\u003c/unittitle\u003e\n                        \u003ccontainer id=\"cid19378022\" type=\"CD\" label=\"Mixed materials\"\u003e1\u003c/container\u003e\n                        \u003ccontainer parent=\"cid19378022\" type=\"item\"\u003eaia048_022\u003c/container\u003e\n                        \u003cunitdate\u003e1909\u003c/unitdate\u003e\n                    \u003c/did\u003e\n                \u003c/c02\u003e\n                \u003cc02 id=\"ref25\" level=\"item\"\u003e\n                    \u003cdid\u003e\n                        \u003cunittitle\u003eNewspaper Clipping: \"Irish-Americans Lead World in Athletic Skills\"; unidentified source, part 1\u003c/unittitle\u003e\n                        \u003ccontainer id=\"cid19378023\" type=\"CD\" label=\"Mixed materials\"\u003e1\u003c/container\u003e\n                        \u003ccontainer parent=\"cid19378023\" type=\"item\"\u003eaia048_023\u003c/container\u003e\n                        \u003cunitdate\u003eundated\u003c/unitdate\u003e\n                    \u003c/did\u003e\n                \u003c/c02\u003e\n                \u003cc02 id=\"ref26\" level=\"item\"\u003e\n                    \u003cdid\u003e\n                        \u003cunittitle\u003eNewspaper Clipping: \"Irish-Americans Lead World in Athletic Skills\"; unidentified source, part 2\u003c/unittitle\u003e\n                        \u003ccontainer id=\"cid19378024\" type=\"CD\" label=\"Mixed materials\"\u003e1\u003c/container\u003e\n                        \u003ccontainer parent=\"cid19378024\" type=\"item\"\u003eaia048_024\u003c/container\u003e\n                        \u003cunitdate\u003eundated\u003c/unitdate\u003e\n                    \u003c/did\u003e\n                \u003c/c02\u003e\n                \u003cc02 id=\"ref27\" level=\"item\"\u003e\n                    \u003cdid\u003e\n                        \u003cunittitle\u003ePhotograph: J.P. Sullivan\u003c/unittitle\u003e\n                        \u003ccontainer id=\"cid19378025\" type=\"CD\" label=\"Mixed materials\"\u003e1\u003c/container\u003e\n                        \u003ccontainer parent=\"cid19378025\" type=\"item\"\u003eaia048_025\u003c/container\u003e\n                        \u003cunitdate\u003eundated\u003c/unitdate\u003e\n                    \u003c/did\u003e\n                \u003c/c02\u003e\n                \u003cc02 id=\"ref28\" level=\"item\"\u003e\n                    \u003cdid\u003e\n                        \u003cunittitle\u003eLetter: from Meyer to Sullivan, page 1\u003c/unittitle\u003e\n                        \u003ccontainer id=\"cid19378026\" type=\"CD\" label=\"Mixed materials\"\u003e1\u003c/container\u003e\n                        \u003ccontainer parent=\"cid19378026\" type=\"item\"\u003eaia048_026\u003c/container\u003e\n                        \u003cunitdate\u003e1908\u003c/unitdate\u003e\n                    \u003c/did\u003e\n                \u003c/c02\u003e\n                \u003cc02 id=\"ref29\" level=\"item\"\u003e\n                    \u003cdid\u003e\n                        \u003cunittitle\u003eLetter: from Meyer to Sullivan, page 2\u003c/unittitle\u003e\n                        \u003ccontainer id=\"cid19378027\" type=\"CD\" label=\"Mixed materials\"\u003e1\u003c/container\u003e\n                        \u003ccontainer parent=\"cid19378027\" type=\"item\"\u003eaia048_027\u003c/container\u003e\n                        \u003cunitdate\u003e1908\u003c/unitdate\u003e\n                    \u003c/did\u003e\n                \u003c/c02\u003e\n                \u003cc02 id=\"ref30\" level=\"item\"\u003e\n                    \u003cdid\u003e\n                        \u003cunittitle\u003eLetter: from Meyer to Sullivan, page 2 (additional image)\u003c/unittitle\u003e\n                        \u003ccontainer id=\"cid19378028\" type=\"CD\" label=\"Mixed materials\"\u003e1\u003c/container\u003e\n                        \u003ccontainer parent=\"cid19378028\" type=\"item\"\u003eaia048_028\u003c/container\u003e\n                        \u003cunitdate\u003e1908\u003c/unitdate\u003e\n                    \u003c/did\u003e\n                \u003c/c02\u003e\n                \u003cc02 id=\"ref31\" level=\"item\"\u003e\n                    \u003cdid\u003e\n                        \u003cunittitle\u003eNewspaper clipping, fragment: Story about the IACC\u003c/unittitle\u003e\n                        \u003ccontainer id=\"cid19378029\" type=\"CD\" label=\"Mixed materials\"\u003e1\u003c/container\u003e\n                        \u003ccontainer parent=\"cid19378029\" type=\"item\"\u003eaia048_029\u003c/container\u003e\n                        \u003cunitdate\u003e1908\u003c/unitdate\u003e\n                    \u003c/did\u003e\n                \u003c/c02\u003e\n                \u003cc02 id=\"ref32\" level=\"item\"\u003e\n                    \u003cdid\u003e\n                        \u003cunittitle\u003eNewspaper clipping \"Will Decorate City in Honor of Athletes\"\u003c/unittitle\u003e\n                        \u003ccontainer id=\"cid19378030\" type=\"CD\" label=\"Mixed materials\"\u003e1\u003c/container\u003e\n                        \u003ccontainer parent=\"cid19378030\" type=\"item\"\u003eaia048_030\u003c/container\u003e\n                        \u003cunitdate\u003e1908\u003c/unitdate\u003e\n                    \u003c/did\u003e\n                \u003c/c02\u003e\n                \u003cc02 id=\"ref33\" level=\"item\"\u003e\n                    \u003cdid\u003e\n                        \u003cunittitle\u003eNewspaper clipping: \n                            \u003cemph render=\"italic\"\u003eNew York American\u003c/emph\u003e \"Irish Club Defeats the New York A.C., 87 to 48\"\u003c/unittitle\u003e\n                        \u003ccontainer id=\"cid19378031\" type=\"CD\" label=\"Mixed materials\"\u003e1\u003c/container\u003e\n                        \u003ccontainer parent=\"cid19378031\" type=\"item\"\u003eaia048_031\u003c/container\u003e\n                        \u003cunitdate\u003eAug 27, 1907\u003c/unitdate\u003e\n                    \u003c/did\u003e\n                \u003c/c02\u003e\n                \u003cc02 id=\"ref34\" level=\"item\"\u003e\n                    \u003cdid\u003e\n                        \u003cunittitle\u003eNewspaper clipping: \n                            \u003cemph render=\"italic\"\u003eNew York Herald\u003c/emph\u003e \"Yankee Athletes Triumph Abr[oad]\"\u003c/unittitle\u003e\n                        \u003ccontainer id=\"cid19378032\" type=\"CD\" label=\"Mixed materials\"\u003e1\u003c/container\u003e\n                        \u003ccontainer parent=\"cid19378032\" type=\"item\"\u003eaia048_032\u003c/container\u003e\n                        \u003cunitdate\u003eJul 14, 1908\u003c/unitdate\u003e\n                    \u003c/did\u003e\n                \u003c/c02\u003e\n                \u003cc02 id=\"ref35\" level=\"item\"\u003e\n                    \u003cdid\u003e\n                        \u003cunittitle\u003eNewspaper clipping: \n                            \u003cemph render=\"italic\"\u003eNew York Press\u003c/emph\u003e \"Training-Camp Life of the Men Who Battle for the Winged Fist\" page 1\u003c/unittitle\u003e\n                        \u003ccontainer id=\"cid19378033\" type=\"CD\" label=\"Mixed materials\"\u003e1\u003c/container\u003e\n                        \u003ccontainer parent=\"cid19378033\" type=\"item\"\u003eaia048_033\u003c/container\u003e\n                        \u003cunitdate\u003eJul 14, 1907\u003c/unitdate\u003e\n                    \u003c/did\u003e\n                \u003c/c02\u003e\n                \u003cc02 id=\"ref36\" level=\"item\"\u003e\n                    \u003cdid\u003e\n                        \u003cunittitle\u003eNewspaper clipping: \n                            \u003cemph render=\"italic\"\u003eNew York Press\u003c/emph\u003e \"Training-Camp Life of the Men Who Battle for the Winged Fist\" page 2\u003c/unittitle\u003e\n                        \u003ccontainer id=\"cid19378034\" type=\"CD\" label=\"Mixed materials\"\u003e1\u003c/container\u003e\n                        \u003ccontainer parent=\"cid19378034\" type=\"item\"\u003eaia048_034\u003c/container\u003e\n                        \u003cunitdate\u003eJul 14, 1907\u003c/unitdate\u003e\n                    \u003c/did\u003e\n                \u003c/c02\u003e\n                \u003cc02 id=\"ref37\" level=\"item\"\u003e\n                    \u003cdid\u003e\n                        \u003cunittitle\u003ePicture, New York [City] Parade \"The Athletes Come Down Fifth Avenue in Automobiles Preceded by the Marathon Trophy on a Float\"\u003c/unittitle\u003e\n                        \u003ccontainer id=\"cid19378035\" type=\"CD\" label=\"Mixed materials\"\u003e1\u003c/container\u003e\n                        \u003ccontainer parent=\"cid19378035\" type=\"item\"\u003eaia048_035\u003c/container\u003e\n                        \u003cunitdate\u003e1908\u003c/unitdate\u003e\n                    \u003c/did\u003e\n                \u003c/c02\u003e\n                \u003cc02 id=\"ref38\" level=\"item\"\u003e\n                    \u003cdid\u003e\n                        \u003cunittitle\u003eNewspaper clipping, fragment: \n                            \u003cemph render=\"italic\"\u003eNew York Times\u003c/emph\u003e \"Pay Final Tribute to Victors\"\u003c/unittitle\u003e\n                        \u003ccontainer id=\"cid19378036\" type=\"CD\" label=\"Mixed materials\"\u003e1\u003c/container\u003e\n                        \u003ccontainer parent=\"cid19378036\" type=\"item\"\u003eaia048_036\u003c/container\u003e\n                        \u003cunitdate\u003eSep 22, 1908\u003c/unitdate\u003e\n                    \u003c/did\u003e\n                \u003c/c02\u003e\n                \u003cc02 id=\"ref39\" level=\"item\"\u003e\n                    \u003cdid\u003e\n                        \u003cunittitle\u003eCertificate Olympic Games 1908: James Sullivan placed 2nd in 1500 meter trials\u003c/unittitle\u003e\n                        \u003ccontainer id=\"cid19378037\" type=\"CD\" label=\"Mixed materials\"\u003e1\u003c/container\u003e\n                        \u003ccontainer parent=\"cid19378037\" type=\"item\"\u003eaia048_037\u003c/container\u003e\n                        \u003cunitdate\u003e1908\u003c/unitdate\u003e\n                    \u003c/did\u003e\n                \u003c/c02\u003e\n                \u003cc02 id=\"ref40\" level=\"item\"\u003e\n                    \u003cdid\u003e\n                        \u003cunittitle\u003eNewspaper clipping: \n                            \u003cemph render=\"italic\"\u003eNew York Press\u003c/emph\u003e \"Crack Distance Runners of Irish-American A.C.\"; depicts Harvey W. Cohn and James P. Sullivan\u003c/unittitle\u003e\n                        \u003ccontainer id=\"cid19378038\" type=\"CD\" label=\"Mixed materials\"\u003e1\u003c/container\u003e\n                        \u003ccontainer parent=\"cid19378038\" type=\"item\"\u003eaia048_038\u003c/container\u003e\n                        \u003cunitdate\u003eJan 7, 1906\u003c/unitdate\u003e\n                    \u003c/did\u003e\n                \u003c/c02\u003e\n                \u003cc02 id=\"ref41\" level=\"item\"\u003e\n                    \u003cdid\u003e\n                        \u003cunittitle\u003eLetter, Department of Correction Commissioner, John Coggey to Egerton L. Winthrop, Jr., President Board of Education offer to give James Sullivan a raise\u003c/unittitle\u003e\n                        \u003ccontainer id=\"cid19378039\" type=\"CD\" label=\"Mixed materials\"\u003e1\u003c/container\u003e\n                        \u003ccontainer parent=\"cid19378039\" type=\"item\"\u003eaia048_039\u003c/container\u003e\n                        \u003cunitdate\u003eJun 29, 1907\u003c/unitdate\u003e\n                    \u003c/did\u003e\n                \u003c/c02\u003e\n                \u003cc02 id=\"ref42\" level=\"item\"\u003e\n                    \u003cdid\u003e\n                        \u003cunittitle\u003e[Minutes?] Department of Education noting James Sullivans request of leave from his position to participate in the 1906 Olympics (granted)\u003c/unittitle\u003e\n                        \u003ccontainer id=\"cid19378040\" type=\"CD\" label=\"Mixed materials\"\u003e1\u003c/container\u003e\n                        \u003ccontainer parent=\"cid19378040\" type=\"item\"\u003eaia048_040\u003c/container\u003e\n                        \u003cunitdate\u003eMar 26, 1906\u003c/unitdate\u003e\n                    \u003c/did\u003e\n                \u003c/c02\u003e\n                \u003cc02 id=\"ref43\" level=\"item\"\u003e\n                    \u003cdid\u003e\n                        \u003cunittitle\u003eCorrespondence: Paul Thompason, Manager, \n                            \u003cemph render=\"italic\"\u003eThe Article Synidcate\u003c/emph\u003e to J.P. Sullivan, Esq. Irish-Americna Athletic Club requesting photograph of Sullivan\u003c/unittitle\u003e\n                        \u003ccontainer id=\"cid19378041\" type=\"CD\" label=\"Mixed materials\"\u003e1\u003c/container\u003e\n                        \u003ccontainer parent=\"cid19378041\" type=\"item\"\u003eaia048_041\u003c/container\u003e\n                        \u003cunitdate\u003eJun 9, 1908\u003c/unitdate\u003e\n                    \u003c/did\u003e\n                \u003c/c02\u003e\n                \u003cc02 id=\"ref44\" level=\"item\"\u003e\n                    \u003cdid\u003e\n                        \u003cunittitle\u003eArticle: \n                            \u003cemph render=\"italic\"\u003eRunning Time\u003c/emph\u003es \"4:22 Jim\" page 1 of 3\u003c/unittitle\u003e\n                        \u003ccontainer id=\"cid19378042\" type=\"CD\" label=\"Mixed materials\"\u003e1\u003c/container\u003e\n                        \u003ccontainer parent=\"cid19378042\" type=\"item\"\u003eaia048_042\u003c/container\u003e\n                        \u003cunitdate\u003eDec 1985\u003c/unitdate\u003e\n                    \u003c/did\u003e\n                \u003c/c02\u003e\n                \u003cc02 id=\"ref45\" level=\"item\"\u003e\n                    \u003cdid\u003e\n                        \u003cunittitle\u003eArticle: \n                            \u003cemph render=\"italic\"\u003eRunning Time\u003c/emph\u003es \"4:22 Jim\" page 2 of 3\u003c/unittitle\u003e\n                        \u003ccontainer id=\"cid19378043\" type=\"CD\" label=\"Mixed materials\"\u003e1\u003c/container\u003e\n                        \u003ccontainer parent=\"cid19378043\" type=\"item\"\u003eaia048_043\u003c/container\u003e\n                        \u003cunitdate\u003eDec 1985\u003c/unitdate\u003e\n                    \u003c/did\u003e\n                \u003c/c02\u003e\n                \u003cc02 id=\"ref46\" level=\"item\"\u003e\n                    \u003cdid\u003e\n                        \u003cunittitle\u003eArticle: \n                            \u003cemph render=\"italic\"\u003eRunning Times\u003c/emph\u003e \"4:22 Jim\" page 3 of 3\u003c/unittitle\u003e\n                        \u003ccontainer id=\"cid19378044\" type=\"CD\" label=\"Mixed materials\"\u003e1\u003c/container\u003e\n                        \u003ccontainer parent=\"cid19378044\" type=\"item\"\u003eaia048_044\u003c/container\u003e\n                        \u003cunitdate\u003eDec 1985\u003c/unitdate\u003e\n                    \u003c/did\u003e\n                \u003c/c02\u003e\n                \u003cc02 id=\"ref47\" level=\"item\"\u003e\n                    \u003cdid\u003e\n                        \u003cunittitle\u003ePicture: Sagamore Hill 1908 with headline \"The Athletes Coming Down Fifth Avenue....\"\u003c/unittitle\u003e\n                        \u003ccontainer id=\"cid19378045\" type=\"CD\" label=\"Mixed materials\"\u003e1\u003c/container\u003e\n                        \u003ccontainer parent=\"cid19378045\" type=\"item\"\u003eaia048_045\u003c/container\u003e\n                        \u003cunitdate\u003e1908\u003c/unitdate\u003e\n                    \u003c/did\u003e\n                \u003c/c02\u003e\n                \u003cc02 id=\"ref48\" level=\"item\"\u003e\n                    \u003cdid\u003e\n                        \u003cunittitle\u003eNewspaper clipping, fragment: Sullivan interview 1958 \"U.S. First No. 1 Miler Still Keeps in Shape\"\u003c/unittitle\u003e\n                        \u003ccontainer id=\"cid19378046\" type=\"CD\" label=\"Mixed materials\"\u003e1\u003c/container\u003e\n                        \u003ccontainer parent=\"cid19378046\" type=\"item\"\u003eaia048_046\u003c/container\u003e\n                        \u003cunitdate\u003e1958\u003c/unitdate\u003e\n                    \u003c/did\u003e\n                \u003c/c02\u003e\n                \u003cc02 id=\"ref49\" level=\"item\"\u003e\n                    \u003cdid\u003e\n                        \u003cunittitle\u003eArticle and picture of Sullivan running \"Athletes who Race at 22nd Regiment Armory To-night\" Pictured: Cohen, Banderman, Sullivan and Freeman\u003c/unittitle\u003e\n                        \u003ccontainer id=\"cid19378047\" type=\"CD\" label=\"Mixed materials\"\u003e1\u003c/container\u003e\n                        \u003ccontainer parent=\"cid19378047\" type=\"item\"\u003eaia048_047\u003c/container\u003e\n                        \u003cunitdate\u003ecirca 1905\u003c/unitdate\u003e\n                    \u003c/did\u003e\n                \u003c/c02\u003e\n                \u003cc02 id=\"ref50\" level=\"item\"\u003e\n                    \u003cdid\u003e\n                        \u003cunittitle\u003ePhotograph: Sullivan in a race\u003c/unittitle\u003e\n                        \u003ccontainer id=\"cid19378048\" type=\"CD\" label=\"Mixed materials\"\u003e1\u003c/container\u003e\n                        \u003ccontainer parent=\"cid19378048\" type=\"item\"\u003eaia048_048\u003c/container\u003e\n                        \u003cunitdate\u003ecirca 1908\u003c/unitdate\u003e\n                    \u003c/did\u003e\n                \u003c/c02\u003e\n                \u003cc02 id=\"ref69\" level=\"item\"\u003e\n                    \u003cdid\u003e\n                        \u003cunittitle\u003eNewspaper clipping: \n                            \u003cemph render=\"italic\"\u003eThe Globe and Commercial Advertiser\u003c/emph\u003e, New York \"Olympic Stars Perform To-Day at Celtic Park\"\u003c/unittitle\u003e\n                        \u003ccontainer id=\"cid19758001\" type=\"CD\" label=\"Mixed materials\"\u003e1\u003c/container\u003e\n                        \u003ccontainer parent=\"cid19758001\" type=\"item\"\u003eaia048_049\u003c/container\u003e\n                        \u003cunitdate\u003eundated\u003c/unitdate\u003e\n                    \u003c/did\u003e\n                \u003c/c02\u003e\n                \u003cc02 id=\"ref52\" level=\"item\"\u003e\n                    \u003cdid\u003e\n                        \u003cunittitle\u003ePage from \n                            \u003cemph render=\"italic\"\u003eThe Graphi\u003c/emph\u003ec \"American Triumps at the Olympic Games\" p. 1\u003c/unittitle\u003e\n                        \u003ccontainer id=\"cid19378050\" type=\"CD\" label=\"Mixed materials\"\u003e1\u003c/container\u003e\n                        \u003ccontainer parent=\"cid19378050\" type=\"item\"\u003eaia048_050\u003c/container\u003e\n                        \u003cunitdate\u003eJul 25, 1908\u003c/unitdate\u003e\n                    \u003c/did\u003e\n                \u003c/c02\u003e\n                \u003cc02 id=\"ref53\" level=\"item\"\u003e\n                    \u003cdid\u003e\n                        \u003cunittitle\u003ePage from \n                            \u003cemph render=\"italic\"\u003eThe Graphic\u003c/emph\u003e \"American Triumps at the Olympic Games\" p. 2\u003c/unittitle\u003e\n                        \u003ccontainer id=\"cid19378051\" type=\"CD\" label=\"Mixed materials\"\u003e1\u003c/container\u003e\n                        \u003ccontainer parent=\"cid19378051\" type=\"item\"\u003eaia048_051\u003c/container\u003e\n                        \u003cunitdate\u003eJul 25, 1909\u003c/unitdate\u003e\n                    \u003c/did\u003e\n                \u003c/c02\u003e\n                \u003cc02 id=\"ref54\" level=\"item\"\u003e\n                    \u003cdid\u003e\n                        \u003cunittitle\u003eNewspaper clipping: \n                            \u003cemph render=\"italic\"\u003eThe Sun\u003c/emph\u003e \"Col. Roosevelt as He Appeared When He Greeted Olympic Team\"\u003c/unittitle\u003e\n                        \u003ccontainer id=\"cid19378052\" type=\"CD\" label=\"Mixed materials\"\u003e1\u003c/container\u003e\n                        \u003ccontainer parent=\"cid19378052\" type=\"item\"\u003eaia048_052\u003c/container\u003e\n                        \u003cunitdate\u003eSep 1, 1908\u003c/unitdate\u003e\n                    \u003c/did\u003e\n                \u003c/c02\u003e\n                \u003cc02 id=\"ref55\" level=\"item\"\u003e\n                    \u003cdid\u003e\n                        \u003cunittitle\u003eNewspaper clipping \n                            \u003cemph render=\"italic\"\u003eThe World\u003c/emph\u003e \"Olympic Team Chosen, They're World Beaters\" p. 1\u003c/unittitle\u003e\n                        \u003ccontainer id=\"cid19378053\" type=\"CD\" label=\"Mixed materials\"\u003e1\u003c/container\u003e\n                        \u003ccontainer parent=\"cid19378053\" type=\"item\"\u003eaia048_053\u003c/container\u003e\n                        \u003cunitdate\u003eJun 9, 1908\u003c/unitdate\u003e\n                    \u003c/did\u003e\n                \u003c/c02\u003e\n                \u003cc02 id=\"ref56\" level=\"item\"\u003e\n                    \u003cdid\u003e\n                        \u003cunittitle\u003eNewspaper clipping \n                            \u003cemph render=\"italic\"\u003eThe World\u003c/emph\u003e \"Olympic Team Chosen, They're World Beaters\" p. 2\u003c/unittitle\u003e\n                        \u003ccontainer id=\"cid19378054\" type=\"CD\" label=\"Mixed materials\"\u003e1\u003c/container\u003e\n                        \u003ccontainer parent=\"cid19378054\" type=\"item\"\u003eaia048_054\u003c/container\u003e\n                        \u003cunitdate\u003eJun 9, 1908\u003c/unitdate\u003e\n                    \u003c/did\u003e\n                \u003c/c02\u003e\n                \u003cc02 id=\"ref57\" level=\"item\"\u003e\n                    \u003cdid\u003e\n                        \u003cunittitle\u003eNewspaper clipping fragment, \n                            \u003cemph render=\"italic\"\u003eThe World\u003c/emph\u003e, Pictures of Melvin Shephard and Jas. P. Sullivan\u003c/unittitle\u003e\n                        \u003ccontainer id=\"cid19378055\" type=\"CD\" label=\"Mixed materials\"\u003e1\u003c/container\u003e\n                        \u003ccontainer parent=\"cid19378055\" type=\"item\"\u003eaia048_055\u003c/container\u003e\n                        \u003cunitdate\u003eJan 25, 1912\u003c/unitdate\u003e\n                    \u003c/did\u003e\n                \u003c/c02\u003e\n                \u003cc02 id=\"ref58\" level=\"item\"\u003e\n                    \u003cdid\u003e\n                        \u003cunittitle\u003ePhotograph: Winning Mile\u003c/unittitle\u003e\n                        \u003ccontainer id=\"cid19378056\" type=\"CD\" label=\"Mixed materials\"\u003e1\u003c/container\u003e\n                        \u003ccontainer parent=\"cid19378056\" type=\"item\"\u003eaia048_056\u003c/container\u003e\n                        \u003cunitdate\u003ecirca 1905\u003c/unitdate\u003e\n                    \u003c/did\u003e\n                \u003c/c02\u003e\n            \u003c/c01\u003e\n        "
        }
    }
}