{
    "eadheader": {
        "countryencoding": "iso3166-1",
        "dateencoding": "iso8601",
        "langencoding": "iso639-2b",
        "repositoryencoding": "iso15511",
        "eadid": {
            "countrycode": "US",
            "mainagencycode": "US-NNU-TL",
            "value": "tam_341"
        },
        "filedesc": {
            "titlestmt": {
                "titleproper": [
                    {
                        "value": "Guide to the Richard Winger: \"Communist Party Candidates for Public Office, 1921 to 1986\" Manuscript\n                    \u003cnum\u003eTAM.341\u003c/num\u003e\n                "
                    }
                ],
                "author": {
                    "value": "Finding aid prepared by Processed by Peter Meyer Filardo"
                }
            },
            "PublicationStmt": {
                "publisher": {
                    "value": "Tamiment Library / Wagner Archives"
                },
                "address": {
                    "addressline": [
                        "Elmer Holmes Bobst Library",
                        "70 Washington Square South",
                        "New York, NY, 10012",
                        "(212) 998-2630",
                        "tamiment.wagner@nyu.edu"
                    ]
                },
                "date": "2009"
            }
        },
        "profiledesc": {
            "creation": {
                "value": "This finding aid was produced using the Archivists' Toolkit\n                \u003cdate\u003e2012-03-29T19:32-0400\u003c/date\u003e\n            "
            },
            "langusage": {
                "language": [
                    {
                        "encodinganalog": "546",
                        "langcode": "eng",
                        "value": "English"
                    }
                ]
            }
        }
    },
    "archdesc": {
        "level": "collection",
        "did": [
            {
                "omitempty": "",
                "repository": {
                    "corpname": {
                        "value": "Tamiment Library / Wagner Archives"
                    }
                },
                "origination": {
                    "label": "creator",
                    "persname": {
                        "source": "local",
                        "value": "Winger, Richard"
                    }
                },
                "unittitle": {
                    "value": "Richard Winger: \"Communist Party Candidates for Public Office, 1921 to 1986\" Manuscript"
                },
                "unitdate": {
                    "normal": "1988/1988",
                    "value": "1988"
                },
                "physdesc": {
                    "extent": [
                        {
                            "value": "0.25 linear feet"
                        },
                        {
                            "value": "(1 box)"
                        }
                    ]
                },
                "abstract": {
                    "label": "Abstract",
                    "value": "This typescript, approximately 250 leaves, was compiled in 1988 by Richard Winger of San Francisco, Calif., from official election returns and the Communist Party press. It lists, by year, national, state, and local candidates for public office who publicly represented themselves as communists, whether or not they were so identified on the election ballot."
                },
                "unitid": {
                    "value": "TAM.341"
                },
                "langmaterial": {
                    "language": {
                        "langcode": "eng"
                    }
                },
                "container": {
                    "id": "cid20124002",
                    "label": "Mixed materials",
                    "type": "Box",
                    "value": "1"
                }
            }
        ],
        "accessrestrict": {
            "id": "ref5",
            "head": "Access Restrictions",
            "p": {
                "value": "Open for research without restrictions."
            }
        },
        "prefercite": {
            "id": "ref24",
            "head": "Preferred Citation",
            "p": {
                "value": "Published citations should take the following form: \n                \u003clb/\u003e\n                \u003clb/\u003eIdentification of item, date; Collection name; Collection number; box number; folder number; \n                \u003clb/\u003eTamiment Library/Robert F. Wagner Labor Archives \n                \u003clb/\u003eElmer Holmes Bobst Library \n                \u003clb/\u003e70 Washington Square South \n                \u003clb/\u003eNew York, NY 10012, New York University Libraries."
            }
        },
        "bioghist": {
            "id": "ref8",
            "head": "Historical/Biographical Note",
            "p": {
                "value": "This typescript, approximately 250 leaves, was compiled in 1988 by Richard Winger of San Francisco, Calif., from official election returns and the Communist Party press."
            }
        },
        "scopecontent": {
            "id": "ref9",
            "head": "Scope and Content Note",
            "p": {
                "value": "This typescript lists, by year, national, state, and local candidates for public office in partisan and non-partisan elections who publicly represented themselves as communists, whether or not they were so identified on the election ballot. The listings including the following information: office sought, candidate's name, votes received, percentage of votes received."
            }
        },
        "controlaccess": {
            "subject": [
                {
                    "source": "lcsh",
                    "value": "Communism |z United States |v Statistics."
                },
                {
                    "source": "lcsh",
                    "value": "Elections |z United States |x History |y 20th century |v Statistics."
                },
                {
                    "source": "lcsh",
                    "value": "Third parties (United States politics) |v Statistics."
                }
            ],
            "corpname": {
                "source": "naf",
                "value": "Communist Party of the United States of America."
            }
        },
        "dsc": {
            "value": "\n            \u003cc01 id=\"ref14\" level=\"series\"\u003e\n                \u003cdid\u003e\n                    \u003cunittitle\u003eSeries I: Communist Party Candidates for Public Office, 1921 to 1986\u003c/unittitle\u003e\n                    \u003clangmaterial\u003e\n                        \u003clanguage langcode=\"eng\"/\u003e\n                    \u003c/langmaterial\u003e\n                \u003c/did\u003e\n                \u003cc02 id=\"ref15\" level=\"file\"\u003e\n                    \u003cdid\u003e\n                        \u003cunittitle\u003eTitle Page, Introduction, Table of Contents\u003c/unittitle\u003e\n                        \u003ccontainer id=\"cid160831\" type=\"Box\" label=\"Mixed materials\"\u003e1\u003c/container\u003e\n                        \u003ccontainer parent=\"cid160831\" type=\"Folder\"\u003e1\u003c/container\u003e\n                        \u003cunitdate normal=\"1988/1988\"\u003e1988\u003c/unitdate\u003e\n                    \u003c/did\u003e\n                \u003c/c02\u003e\n                \u003cc02 id=\"ref16\" level=\"file\"\u003e\n                    \u003cdid\u003e\n                        \u003cunittitle\u003eCandidates: 1920s\u003c/unittitle\u003e\n                        \u003ccontainer id=\"cid160830\" type=\"Box\" label=\"Mixed materials\"\u003e1\u003c/container\u003e\n                        \u003ccontainer parent=\"cid160830\" type=\"Folder\"\u003e2\u003c/container\u003e\n                        \u003cunitdate normal=\"1988/1988\"\u003e1988\u003c/unitdate\u003e\n                    \u003c/did\u003e\n                \u003c/c02\u003e\n                \u003cc02 id=\"ref17\" level=\"file\"\u003e\n                    \u003cdid\u003e\n                        \u003cunittitle\u003eCandidates: 1930s\u003c/unittitle\u003e\n                        \u003ccontainer id=\"cid160829\" type=\"Box\" label=\"Mixed materials\"\u003e1\u003c/container\u003e\n                        \u003ccontainer parent=\"cid160829\" type=\"Folder\"\u003e3\u003c/container\u003e\n                        \u003cunitdate normal=\"1988/1988\"\u003e1988\u003c/unitdate\u003e\n                    \u003c/did\u003e\n                \u003c/c02\u003e\n                \u003cc02 id=\"ref18\" level=\"file\"\u003e\n                    \u003cdid\u003e\n                        \u003cunittitle\u003eCandidates: 1940s\u003c/unittitle\u003e\n                        \u003ccontainer id=\"cid160828\" type=\"Box\" label=\"Mixed materials\"\u003e1\u003c/container\u003e\n                        \u003ccontainer parent=\"cid160828\" type=\"Folder\"\u003e4\u003c/container\u003e\n                        \u003cunitdate normal=\"1988/1988\"\u003e1988\u003c/unitdate\u003e\n                    \u003c/did\u003e\n                \u003c/c02\u003e\n                \u003cc02 id=\"ref19\" level=\"file\"\u003e\n                    \u003cdid\u003e\n                        \u003cunittitle\u003eCandidates: 1950s\u003c/unittitle\u003e\n                        \u003ccontainer id=\"cid160827\" type=\"Box\" label=\"Mixed materials\"\u003e1\u003c/container\u003e\n                        \u003ccontainer parent=\"cid160827\" type=\"Folder\"\u003e5\u003c/container\u003e\n                        \u003cunitdate normal=\"1988/1988\"\u003e1988\u003c/unitdate\u003e\n                    \u003c/did\u003e\n                \u003c/c02\u003e\n                \u003cc02 id=\"ref20\" level=\"file\"\u003e\n                    \u003cdid\u003e\n                        \u003cunittitle\u003eCandidates: 1960s\u003c/unittitle\u003e\n                        \u003ccontainer id=\"cid160826\" type=\"Box\" label=\"Mixed materials\"\u003e1\u003c/container\u003e\n                        \u003ccontainer parent=\"cid160826\" type=\"Folder\"\u003e6\u003c/container\u003e\n                        \u003cunitdate normal=\"1988/1988\"\u003e1988\u003c/unitdate\u003e\n                    \u003c/did\u003e\n                \u003c/c02\u003e\n                \u003cc02 id=\"ref21\" level=\"file\"\u003e\n                    \u003cdid\u003e\n                        \u003cunittitle\u003eCandidates: 1970s\u003c/unittitle\u003e\n                        \u003ccontainer id=\"cid160825\" type=\"Box\" label=\"Mixed materials\"\u003e1\u003c/container\u003e\n                        \u003ccontainer parent=\"cid160825\" type=\"Folder\"\u003e7\u003c/container\u003e\n                        \u003cunitdate normal=\"1988/1988\"\u003e1988\u003c/unitdate\u003e\n                    \u003c/did\u003e\n                \u003c/c02\u003e\n                \u003cc02 id=\"ref22\" level=\"file\"\u003e\n                    \u003cdid\u003e\n                        \u003cunittitle\u003eCandidates: 1980s\u003c/unittitle\u003e\n                        \u003ccontainer id=\"cid160824\" type=\"Box\" label=\"Mixed materials\"\u003e1\u003c/container\u003e\n                        \u003ccontainer parent=\"cid160824\" type=\"Folder\"\u003e8\u003c/container\u003e\n                        \u003cunitdate normal=\"1988/1988\"\u003e1988\u003c/unitdate\u003e\n                    \u003c/did\u003e\n                \u003c/c02\u003e\n            \u003c/c01\u003e\n        "
        }
    }
}