{
    "eadheader": {
        "countryencoding": "iso3166-1",
        "dateencoding": "iso8601",
        "langencoding": "iso639-2b",
        "repositoryencoding": "iso15511",
        "eadid": {
            "countrycode": "US",
            "mainagencycode": "US-NHi",
            "value": "gillespie"
        },
        "filedesc": {
            "titlestmt": {
                "titleproper": [
                    {
                        "value": "Guide to the Paul Gillespie Collection of \n                    \u003clb/\u003eNew York World's Fair Materials\n                    \u003clb/\u003e\n                    \u003cdate\u003e1936-2010\u003c/date\u003e\n                    \u003clb/\u003e\n                    \u003cnum\u003e\u003c/num\u003e\n                    \u003cnum\u003ePR 283\u003c/num\u003e\n                "
                    }
                ],
                "author": {
                    "value": "Finding aid prepared by Kenneth Cleary"
                }
            },
            "PublicationStmt": {
                "publisher": {
                    "value": "© 2011 New-York Historical Society"
                },
                "address": {
                    "addressline": [
                        "New-York Historical Society",
                        "170 Central Park West",
                        "New York, NY 10024",
                        "Phone: (212) 873-3400"
                    ]
                },
                "date": "July 2011"
            }
        },
        "profiledesc": {
            "creation": {
                "value": "This finding aid was produced using the Archivists' Toolkit\n                \u003cdate\u003e2011-11-10T16:29-0500\u003c/date\u003e\n            "
            }
        }
    },
    "archdesc": {
        "level": "collection",
        "did": [
            {
                "omitempty": "",
                "repository": {
                    "corpname": {
                        "value": "© 2011 New-York Historical Society"
                    }
                },
                "unittitle": {
                    "value": "Paul Gillespie Collection of New York World's Fair Materials"
                },
                "unitdate": {
                    "normal": "1936/2010",
                    "type": "inclusive",
                    "value": "1936-2010 (Bulk 1939-1940)"
                },
                "physdesc": {
                    "extent": [
                        {
                            "value": "16.87 Linear feet"
                        }
                    ]
                },
                "abstract": {
                    "label": "Abstract",
                    "value": "Photographs and ephemera from the 1939-40 New York World's Fair collected by Paul Gillespie."
                },
                "unitid": {
                    "value": "PR 283"
                },
                "langmaterial": {
                    "language": {
                        "langcode": "eng"
                    }
                }
            }
        ],
        "accessrestrict": {
            "id": "ref52",
            "head": "Access",
            "p": {
                "value": "The collection is open to qualified researchers. Portions of the collection that have been photocopied or microfilmed will be brought to the researcher in that format; microfilm can be made available through Interlibrary Loan."
            }
        },
        "prefercite": {
            "id": "ref55",
            "head": "Citation",
            "p": {
                "value": "This collection should be cited as: Paul Gillespie Collection of New York World's Fair Materials, PR 283, Department of Prints, Photographs, and Architectural Collections, The New-York Historical Society."
            }
        },
        "acqinfo": {
            "id": "ref54",
            "head": "Provenance",
            "p": {
                "value": "Gift of Paul Gillespie, 2011."
            }
        },
        "bioghist": {
            "id": "ref144",
            "head": "Historical Note",
            "p": {
                "value": "By the time the fair's second season opened, many of the participating nations were engulfed in the Second World War, leading some to either withdraw from the fair or causing their delegations to become exiles in America. In response, the slogan of the fair was changed to \"For Peace and Freedom\" and new patriotic themes prevailed. In an effort to attract more visitors, the price of admission was lowered and a greater emphasis was placed on marketing the fair's amusements. Despite these changes the fair did not last past its second season and would ultimately declare bankruptcy. However, the legacy of the fair would remain in the post-war memories of Americans who would go on to create a cultural landscape that in many ways resembled the prosperous, streamlined, middle-class world that the fair had imagined."
            }
        },
        "scopecontent": {
            "id": "ref145",
            "head": "Scope and Content",
            "p": {
                "value": "A small amount of material relating to the 1964-65 New York World's Fair, the Golden Gate International Exposition and other world fairs is also found in this collection."
            }
        },
        "controlaccess": {
            "subject": [
                {
                    "source": "lcsh",
                    "value": "Amusement parks--History."
                },
                {
                    "source": "lcsh",
                    "value": "Burlesque (Theater)--History."
                },
                {
                    "source": "lcsh",
                    "value": "Exhibition buildings -- New York (State) -- New York"
                },
                {
                    "source": "lcsh",
                    "value": "Exhibitions--New York (State)--New York. "
                },
                {
                    "source": "lcsh",
                    "value": "Freak shows--United States--History."
                },
                {
                    "source": "lcsh",
                    "value": "International relations and culture."
                },
                {
                    "source": "lcsh",
                    "value": "Lighting, Architectural and decorative--History--20th century."
                },
                {
                    "source": "lcsh",
                    "value": "New York World's Fair--(1939-1940)"
                },
                {
                    "source": "lcsh",
                    "value": "World War, 1939-1945 Refugees"
                },
                {
                    "source": "lcsh",
                    "value": "World War, 1939-1945--Propaganda--Public opinion."
                }
            ]
        },
        "dsc": {
            "value": "\n            \u003cc id=\"ref1\" level=\"series\"\u003e\n                \u003cdid\u003e\n                    \u003cunittitle\u003eSeries I. Photographs\u003c/unittitle\u003e\n                    \u003cunitdate normal=\"1936/1940\" type=\"inclusive\"\u003e1936-1940\u003c/unitdate\u003e\n                \u003c/did\u003e\n                \u003cscopecontent id=\"ref206\"\u003e\n                    \u003chead\u003eSee Also\u003c/head\u003e\n                    \u003cp\u003eSeries VII. Oversize Materials\u003c/p\u003e\n                \u003c/scopecontent\u003e\n                \u003cscopecontent id=\"ref153\"\u003e\n                    \u003chead\u003eScope and Content\u003c/head\u003e\n                    \u003cp\u003eThere are approximately 3,500 loose photographs in a wide variety of formats, from as small as 1.5 x 2.25 inches to as large as 16 x 20 inches. The majority of photographs are gelatin silver prints, but there are more than two hundred color photographs as well. Also within this series are an assortment of stereographs and twenty-six, 4 x 5 inch Kodachrome direct positive transparencies.\u003c/p\u003e\n                    \u003cp\u003eDue to the range of formats and levels of identification, this series has been further divided into nine subseries:\u003c/p\u003e\n                    \u003clist type=\"ordered\"\u003e\n                        \u003citem\u003eSubseries I. World's Fair Publicity\u003c/item\u003e\n                        \u003citem\u003eSubseries II. Press Photographs\u003c/item\u003e\n                        \u003citem\u003eSubseries III. General Electric Snapshot Contest\u003c/item\u003e\n                        \u003citem\u003eSubseries IV. The Bettmann Archive\u003c/item\u003e\n                        \u003citem\u003eSubseries VI. Unidentified Photographers\u003c/item\u003e\n                        \u003citem\u003eSubseries V. Identified Photographers\u003c/item\u003e\n                        \u003citem\u003eSubseries VII. Photographs from other Institutions\u003c/item\u003e\n                        \u003citem\u003eSubseries VIII. Other World Fairs\u003c/item\u003e\n                        \u003citem\u003eSubseries IX. Stereographs\u003c/item\u003e\n                    \u003c/list\u003e\n                \u003c/scopecontent\u003e\n                \u003cc id=\"ref9\" level=\"subseries\"\u003e\n                    \u003cdid\u003e\n                        \u003cunittitle\u003eSubseries I. World's Fair Publicity\u003c/unittitle\u003e\n                    \u003c/did\u003e\n                    \u003cscopecontent id=\"ref154\"\u003e\n                        \u003chead\u003eScope and Content\u003c/head\u003e\n                        \u003cp\u003eThis subseries contains a variety of 8 x 10 inch photographs taken by New York World's Fair Corporation photographers and disseminated by the New York's World's Fair Publicity / Public Relations Office. Many include narrative material on the reverse side of the photograph.\u003c/p\u003e\n                    \u003c/scopecontent\u003e\n                    \u003cc id=\"ref57\" level=\"file\"\u003e\n                        \u003cdid\u003e\n                            \u003cunittitle\u003ePublicity Photos\u003c/unittitle\u003e\n                            \u003ccontainer id=\"cid418001\" type=\"Box\" label=\"Graphic materials\"\u003e1\u003c/container\u003e\n                            \u003ccontainer parent=\"cid418001\" type=\"Folder\"\u003e1-2\u003c/container\u003e\n                            \u003cunitdate\u003e1939\u003c/unitdate\u003e\n                        \u003c/did\u003e\n                    \u003c/c\u003e\n                    \u003cc id=\"ref58\" level=\"file\"\u003e\n                        \u003cdid\u003e\n                            \u003cunittitle\u003ePublicity Photos\u003c/unittitle\u003e\n                            \u003ccontainer id=\"cid418003\" type=\"Box\" label=\"Graphic materials\"\u003e1\u003c/container\u003e\n                            \u003ccontainer parent=\"cid418003\" type=\"Folder\"\u003e3-5\u003c/container\u003e\n                            \u003cunitdate\u003e1940\u003c/unitdate\u003e\n                        \u003c/did\u003e\n                    \u003c/c\u003e\n                \u003c/c\u003e\n                \u003cc id=\"ref8\" level=\"subseries\"\u003e\n                    \u003cdid\u003e\n                        \u003cunittitle\u003eSubseries II. Press Photographs\u003c/unittitle\u003e\n                    \u003c/did\u003e\n                    \u003cscopecontent id=\"ref156\"\u003e\n                        \u003chead\u003eScope and Content\u003c/head\u003e\n                        \u003cp\u003eThis subseries consists of 8 x 10 inch photographs taken by news corporations or agencies.\u003c/p\u003e\n                    \u003c/scopecontent\u003e\n                    \u003cc id=\"ref14\" level=\"file\"\u003e\n                        \u003cdid\u003e\n                            \u003cunittitle\u003eACME\u003c/unittitle\u003e\n                            \u003ccontainer id=\"cid418006\" type=\"Box\" label=\"Graphic materials\"\u003e1\u003c/container\u003e\n                            \u003ccontainer parent=\"cid418006\" type=\"Folder\"\u003e6\u003c/container\u003e\n                            \u003cunitdate\u003e1939-1940\u003c/unitdate\u003e\n                        \u003c/did\u003e\n                    \u003c/c\u003e\n                    \u003cc id=\"ref29\" level=\"file\"\u003e\n                        \u003cdid\u003e\n                            \u003cunittitle\u003eAssociated Press\u003c/unittitle\u003e\n                            \u003ccontainer id=\"cid418007\" type=\"Box\" label=\"Graphic materials\"\u003e1\u003c/container\u003e\n                            \u003ccontainer parent=\"cid418007\" type=\"Folder\"\u003e7\u003c/container\u003e\n                            \u003cunitdate\u003e1939-1940\u003c/unitdate\u003e\n                        \u003c/did\u003e\n                    \u003c/c\u003e\n                    \u003cc id=\"ref20\" level=\"file\"\u003e\n                        \u003cdid\u003e\n                            \u003cunittitle\u003eHerarld Tribune\u003c/unittitle\u003e\n                            \u003ccontainer id=\"cid418008\" type=\"Box\" label=\"Graphic materials\"\u003e1\u003c/container\u003e\n                            \u003ccontainer parent=\"cid418008\" type=\"Folder\"\u003e8\u003c/container\u003e\n                            \u003cunitdate\u003e1939-1940\u003c/unitdate\u003e\n                        \u003c/did\u003e\n                    \u003c/c\u003e\n                    \u003cc id=\"ref21\" level=\"file\"\u003e\n                        \u003cdid\u003e\n                            \u003cunittitle\u003eInternational News\u003c/unittitle\u003e\n                            \u003ccontainer id=\"cid418009\" type=\"Box\" label=\"Graphic materials\"\u003e1\u003c/container\u003e\n                            \u003ccontainer parent=\"cid418009\" type=\"Folder\"\u003e9\u003c/container\u003e\n                            \u003cunitdate\u003e1939-1940\u003c/unitdate\u003e\n                        \u003c/did\u003e\n                    \u003c/c\u003e\n                    \u003cc id=\"ref16\" level=\"file\"\u003e\n                        \u003cdid\u003e\n                            \u003cunittitle\u003eWide World Photos\u003c/unittitle\u003e\n                            \u003ccontainer id=\"cid418010\" type=\"Box\" label=\"Graphic materials\"\u003e1\u003c/container\u003e\n                            \u003ccontainer parent=\"cid418010\" type=\"Folder\"\u003e10\u003c/container\u003e\n                            \u003cunitdate\u003e1939-1940\u003c/unitdate\u003e\n                        \u003c/did\u003e\n                    \u003c/c\u003e\n                \u003c/c\u003e\n                \u003cc id=\"ref31\" level=\"subseries\"\u003e\n                    \u003cdid\u003e\n                        \u003cunittitle\u003eSubseries III. General Electric Snapshot Contest\u003c/unittitle\u003e\n                        \u003cunitdate\u003e1939-1940\u003c/unitdate\u003e\n                    \u003c/did\u003e\n                    \u003cscopecontent id=\"ref59\"\u003e\n                        \u003chead\u003eScope and Content\u003c/head\u003e\n                        \u003cp\u003eThis subseries consists of amateur photographs entered in a contest sponsored by General Electric.\u003c/p\u003e\n                    \u003c/scopecontent\u003e\n                    \u003cc id=\"ref194\" level=\"file\"\u003e\n                        \u003cdid\u003e\n                            \u003cunittitle\u003eGeneral Electric Snapshot Contest\u003c/unittitle\u003e\n                            \u003ccontainer id=\"cid451001\" type=\"Box\" label=\"Graphic materials\"\u003e1\u003c/container\u003e\n                            \u003ccontainer parent=\"cid451001\" type=\"Folder\"\u003e11\u003c/container\u003e\n                            \u003cunitdate\u003e1939-1940\u003c/unitdate\u003e\n                        \u003c/did\u003e\n                    \u003c/c\u003e\n                \u003c/c\u003e\n                \u003cc id=\"ref13\" level=\"subseries\"\u003e\n                    \u003cdid\u003e\n                        \u003cunittitle\u003eSubseries IV. The Bettmann Archive\u003c/unittitle\u003e\n                    \u003c/did\u003e\n                    \u003cscopecontent id=\"ref157\"\u003e\n                        \u003chead\u003eScope and Content\u003c/head\u003e\n                        \u003cp\u003eThis subseries consists of 8 x 10 inch photographs from the Bettmann Archive.\u003c/p\u003e\n                    \u003c/scopecontent\u003e\n                    \u003cc id=\"ref195\" level=\"file\"\u003e\n                        \u003cdid\u003e\n                            \u003cunittitle\u003eThe Bettmann Archive\u003c/unittitle\u003e\n                            \u003ccontainer id=\"cid451002\" type=\"Box\" label=\"Graphic materials\"\u003e1\u003c/container\u003e\n                            \u003ccontainer parent=\"cid451002\" type=\"Folder\"\u003e12\u003c/container\u003e\n                            \u003cunitdate\u003e1939-1940\u003c/unitdate\u003e\n                        \u003c/did\u003e\n                    \u003c/c\u003e\n                \u003c/c\u003e\n                \u003cc id=\"ref7\" level=\"subseries\"\u003e\n                    \u003cdid\u003e\n                        \u003cunittitle\u003eSubseries V. Identified Photographers\u003c/unittitle\u003e\n                    \u003c/did\u003e\n                    \u003cscopecontent id=\"ref158\"\u003e\n                        \u003chead\u003eScope and Content\u003c/head\u003e\n                        \u003cp\u003eThis subseries consists mostly of 8 x 10 inch photographs bearing ownership stamps from individual photographers, including some known professionals. The largest collection is from Underwood \u0026amp; Underwood, a prominent commercial photography company that was employed by the World's Fair Corporation Publicity Department. The Underwood \u0026amp; Underwood file also contains a packaged collection titled, \"Official Photographs New York World's Fair 1939.\" Other significant items in this subseries include nearly 200 color photographs taken by Conrad H. Ruppert using Kodak's new Kodachrome transparency film. There are also a number of aerial photographs taken by Rudy Arnold and McLaughlin Air Service that show the fair grounds prior to and during construction.\u003c/p\u003e\n                    \u003c/scopecontent\u003e\n                    \u003cc id=\"ref30\" level=\"file\"\u003e\n                        \u003cdid\u003e\n                            \u003cunittitle\u003eRudy Arnold\u003c/unittitle\u003e\n                            \u003ccontainer id=\"cid414001\" type=\"Box\" label=\"Graphic materials\"\u003e2\u003c/container\u003e\n                            \u003ccontainer parent=\"cid414001\" type=\"Folder\"\u003e1\u003c/container\u003e\n                            \u003cunitdate\u003e1937-1938\u003c/unitdate\u003e\n                        \u003c/did\u003e\n                    \u003c/c\u003e\n                    \u003cc id=\"ref25\" level=\"file\"\u003e\n                        \u003cdid\u003e\n                            \u003cunittitle\u003eH. Baranger\u003c/unittitle\u003e\n                            \u003ccontainer id=\"cid414002\" type=\"Box\" label=\"Graphic materials\"\u003e2\u003c/container\u003e\n                            \u003ccontainer parent=\"cid414002\" type=\"Folder\"\u003e2\u003c/container\u003e\n                            \u003cunitdate\u003e1939-1940\u003c/unitdate\u003e\n                        \u003c/did\u003e\n                    \u003c/c\u003e\n                    \u003cc id=\"ref19\" level=\"file\"\u003e\n                        \u003cdid\u003e\n                            \u003cunittitle\u003eGeorge A. Douglas\u003c/unittitle\u003e\n                            \u003ccontainer id=\"cid415002\" type=\"Box\" label=\"Graphic materials\"\u003e2\u003c/container\u003e\n                            \u003ccontainer parent=\"cid415002\" type=\"Folder\"\u003e3\u003c/container\u003e\n                            \u003cunitdate\u003e1939-1940\u003c/unitdate\u003e\n                        \u003c/did\u003e\n                    \u003c/c\u003e\n                    \u003cc id=\"ref18\" level=\"file\"\u003e\n                        \u003cdid\u003e\n                            \u003cunittitle\u003eSamuel H. Gottscho\u003c/unittitle\u003e\n                            \u003ccontainer id=\"cid415003\" type=\"Box\" label=\"Graphic materials\"\u003e2\u003c/container\u003e\n                            \u003ccontainer parent=\"cid415003\" type=\"Folder\"\u003e4\u003c/container\u003e\n                            \u003cunitdate\u003e1939-1940\u003c/unitdate\u003e\n                        \u003c/did\u003e\n                    \u003c/c\u003e\n                    \u003cc id=\"ref27\" level=\"file\"\u003e\n                        \u003cdid\u003e\n                            \u003cunittitle\u003eMcLaughlin Air Sevice\u003c/unittitle\u003e\n                            \u003ccontainer id=\"cid415004\" type=\"Box\" label=\"Graphic materials\"\u003e2\u003c/container\u003e\n                            \u003ccontainer parent=\"cid415004\" type=\"Folder\"\u003e5\u003c/container\u003e\n                            \u003cunitdate\u003e1936,1939\u003c/unitdate\u003e\n                        \u003c/did\u003e\n                    \u003c/c\u003e\n                    \u003cc id=\"ref11\" level=\"file\"\u003e\n                        \u003cdid\u003e\n                            \u003cunittitle\u003eConrad H. Ruppert\u003c/unittitle\u003e\n                            \u003ccontainer id=\"cid415005\" type=\"Box\" label=\"Graphic materials\"\u003e2\u003c/container\u003e\n                            \u003ccontainer parent=\"cid415005\" type=\"Folder\"\u003e6-9\u003c/container\u003e\n                            \u003cunitdate\u003e1939-1940\u003c/unitdate\u003e\n                        \u003c/did\u003e\n                    \u003c/c\u003e\n                    \u003cc id=\"ref17\" level=\"file\"\u003e\n                        \u003cdid\u003e\n                            \u003cunittitle\u003eA. F. Sozio\u003c/unittitle\u003e\n                            \u003ccontainer id=\"cid415009\" type=\"Box\" label=\"Graphic materials\"\u003e2\u003c/container\u003e\n                            \u003ccontainer parent=\"cid415009\" type=\"Folder\"\u003e10\u003c/container\u003e\n                            \u003cunitdate\u003e1939-1940\u003c/unitdate\u003e\n                        \u003c/did\u003e\n                    \u003c/c\u003e\n                    \u003cc id=\"ref12\" level=\"file\"\u003e\n                        \u003cdid\u003e\n                            \u003cunittitle\u003eUnderwood \u0026amp; Underwood\u003c/unittitle\u003e\n                            \u003ccontainer id=\"cid415010\" type=\"Box\" label=\"Graphic materials\"\u003e2\u003c/container\u003e\n                            \u003ccontainer parent=\"cid415010\" type=\"Folder\"\u003e11-13\u003c/container\u003e\n                            \u003cunitdate\u003e1939-1940\u003c/unitdate\u003e\n                        \u003c/did\u003e\n                    \u003c/c\u003e\n                    \u003cc id=\"ref64\" level=\"file\"\u003e\n                        \u003cdid\u003e\n                            \u003cunittitle\u003eUnderwood \u0026amp; Underwood\u003c/unittitle\u003e\n                            \u003ccontainer id=\"cid415011\" type=\"Box\" label=\"Graphic materials\"\u003e3\u003c/container\u003e\n                            \u003ccontainer parent=\"cid415011\" type=\"Folder\"\u003e1-4\u003c/container\u003e\n                            \u003cunitdate\u003e1939-1940\u003c/unitdate\u003e\n                        \u003c/did\u003e\n                    \u003c/c\u003e\n                    \u003cc id=\"ref26\" level=\"file\"\u003e\n                        \u003cdid\u003e\n                            \u003cunittitle\u003eCarl Van Vechten\u003c/unittitle\u003e\n                            \u003ccontainer id=\"cid415016\" type=\"Box\" label=\"Graphic materials\"\u003e3\u003c/container\u003e\n                            \u003ccontainer parent=\"cid415016\" type=\"Folder\"\u003e5\u003c/container\u003e\n                            \u003cunitdate\u003e1939-1940\u003c/unitdate\u003e\n                        \u003c/did\u003e\n                    \u003c/c\u003e\n                    \u003cc id=\"ref15\" level=\"file\"\u003e\n                        \u003cdid\u003e\n                            \u003cunittitle\u003eMiscellaneous Photographers\u003c/unittitle\u003e\n                            \u003ccontainer id=\"cid416001\" type=\"Box\" label=\"Graphic materials\"\u003e3\u003c/container\u003e\n                            \u003ccontainer parent=\"cid416001\" type=\"Folder\"\u003e6\u003c/container\u003e\n                            \u003cunitdate\u003e1939-1940\u003c/unitdate\u003e\n                        \u003c/did\u003e\n                    \u003c/c\u003e\n                \u003c/c\u003e\n                \u003cc id=\"ref10\" level=\"subseries\"\u003e\n                    \u003cdid\u003e\n                        \u003cunittitle\u003eSubseries VI. Unidentified Photographers\u003c/unittitle\u003e\n                    \u003c/did\u003e\n                    \u003cscopecontent id=\"ref159\"\u003e\n                        \u003chead\u003eScope and Content\u003c/head\u003e\n                        \u003cp\u003eThis subseries is the largest part of the Gillespie collection and consists of a large assortment of photographs by unknown photographers, covering a variety of subjects, styles and formats. The photographs capture almost every aspect of the fair, including pictures of the fair under construction and images inside exhibits and shows. Many photographs have a distinctly amateur quality in their choice of subject and composition, but a significant number demonstrate an advanced level of skill.\u003c/p\u003e\n                        \u003cp\u003ePhotographs in this subseries are arranged by size and format. If sleeved, they are done so back-to-back if no useful information is written on the reverse. Large photographs are mostly 8 x 10 inches or similar in size. Medium photographs are mainly in the range of 4 x 6 inches to 5 x 7 inches; Box 5, folders 6 through 8 were originally bound together as a single album, but were rehoused for conservation purposes. Included in the medium category are three folders that originally came from a single bound collection of vinyl sleeves. Small photographs are mostly smaller than 4 x 6 inches. This category also includes two sets of small souvenir photo cards that are still in their original packaging. Color positives are twenty-six, 4 x 5 Kodachrome direct positive transparencies.\u003c/p\u003e\n                    \u003c/scopecontent\u003e\n                    \u003cc id=\"ref50\" level=\"file\"\u003e\n                        \u003cdid\u003e\n                            \u003cunittitle\u003eLarge Photographs\u003c/unittitle\u003e\n                            \u003ccontainer id=\"cid419002\" type=\"Box\" label=\"Graphic materials\"\u003e3\u003c/container\u003e\n                            \u003ccontainer parent=\"cid419002\" type=\"Folder\"\u003e7-8\u003c/container\u003e\n                            \u003cunitdate\u003e1939-1940\u003c/unitdate\u003e\n                        \u003c/did\u003e\n                    \u003c/c\u003e\n                    \u003cc id=\"ref73\" level=\"file\"\u003e\n                        \u003cdid\u003e\n                            \u003cunittitle\u003eLarge Photographs\u003c/unittitle\u003e\n                            \u003ccontainer id=\"cid419003\" type=\"Box\" label=\"Graphic materials\"\u003e4\u003c/container\u003e\n                            \u003ccontainer parent=\"cid419003\" type=\"Folder\"\u003e1-7\u003c/container\u003e\n                            \u003cunitdate\u003e1939-1940\u003c/unitdate\u003e\n                        \u003c/did\u003e\n                    \u003c/c\u003e\n                    \u003cc id=\"ref74\" level=\"file\"\u003e\n                        \u003cdid\u003e\n                            \u003cunittitle\u003eLarge Photographs\u003c/unittitle\u003e\n                            \u003ccontainer id=\"cid419004\" type=\"Box\" label=\"Graphic materials\"\u003e5\u003c/container\u003e\n                            \u003ccontainer parent=\"cid419004\" type=\"Folder\"\u003e1-3\u003c/container\u003e\n                            \u003cunitdate\u003e1939-1940\u003c/unitdate\u003e\n                        \u003c/did\u003e\n                    \u003c/c\u003e\n                    \u003cc id=\"ref92\" level=\"file\"\u003e\n                        \u003cdid\u003e\n                            \u003cunittitle\u003eLarge - Color\u003c/unittitle\u003e\n                            \u003ccontainer id=\"cid420013\" type=\"Box\" label=\"Graphic materials\"\u003e5\u003c/container\u003e\n                            \u003ccontainer parent=\"cid420013\" type=\"Folder\"\u003e4\u003c/container\u003e\n                            \u003cunitdate\u003e1939-1940\u003c/unitdate\u003e\n                        \u003c/did\u003e\n                    \u003c/c\u003e\n                    \u003cc id=\"ref126\" level=\"file\"\u003e\n                        \u003cdid\u003e\n                            \u003cunittitle\u003eMedium Photographs\u003c/unittitle\u003e\n                            \u003ccontainer id=\"cid436001\" type=\"Box\" label=\"Graphic materials\"\u003e5\u003c/container\u003e\n                            \u003ccontainer parent=\"cid436001\" type=\"Folder\"\u003e5-8\u003c/container\u003e\n                            \u003cunitdate\u003e1939-1940\u003c/unitdate\u003e\n                        \u003c/did\u003e\n                    \u003c/c\u003e\n                    \u003cc id=\"ref84\" level=\"file\"\u003e\n                        \u003cdid\u003e\n                            \u003cunittitle\u003eMedium Photographs\u003c/unittitle\u003e\n                            \u003ccontainer id=\"cid420006\" type=\"Box\" label=\"Graphic materials\"\u003e6\u003c/container\u003e\n                            \u003ccontainer parent=\"cid420006\" type=\"Folder\"\u003e1-4\u003c/container\u003e\n                            \u003cunitdate\u003e1939-1940\u003c/unitdate\u003e\n                        \u003c/did\u003e\n                    \u003c/c\u003e\n                    \u003cc id=\"ref85\" level=\"file\"\u003e\n                        \u003cdid\u003e\n                            \u003cunittitle\u003eMedium Photographs\u003c/unittitle\u003e\n                            \u003ccontainer id=\"cid420007\" type=\"Box\" label=\"Graphic materials\"\u003e7\u003c/container\u003e\n                            \u003ccontainer parent=\"cid420007\" type=\"Folder\"\u003e1-4\u003c/container\u003e\n                            \u003cunitdate\u003e1939-1940\u003c/unitdate\u003e\n                        \u003c/did\u003e\n                    \u003c/c\u003e\n                    \u003cc id=\"ref86\" level=\"file\"\u003e\n                        \u003cdid\u003e\n                            \u003cunittitle\u003eMedium Photographs\u003c/unittitle\u003e\n                            \u003ccontainer id=\"cid420008\" type=\"Box\" label=\"Graphic materials\"\u003e8\u003c/container\u003e\n                            \u003ccontainer parent=\"cid420008\" type=\"Folder\"\u003e1-3\u003c/container\u003e\n                            \u003cunitdate\u003e1939-1940\u003c/unitdate\u003e\n                        \u003c/did\u003e\n                    \u003c/c\u003e\n                    \u003cc id=\"ref88\" level=\"file\"\u003e\n                        \u003cdid\u003e\n                            \u003cunittitle\u003eMedium - Color\u003c/unittitle\u003e\n                            \u003ccontainer id=\"cid421004\" type=\"Box\" label=\"Graphic materials\"\u003e8\u003c/container\u003e\n                            \u003ccontainer parent=\"cid421004\" type=\"Folder\"\u003e4\u003c/container\u003e\n                            \u003cunitdate\u003e1939-1940\u003c/unitdate\u003e\n                        \u003c/did\u003e\n                    \u003c/c\u003e\n                    \u003cc id=\"ref48\" level=\"item\"\u003e\n                        \u003cdid\u003e\n                            \u003cunittitle\u003eSmall Photographs\u003c/unittitle\u003e\n                            \u003ccontainer id=\"cid421005\" type=\"Box\" label=\"Graphic materials\"\u003e9\u003c/container\u003e\n                            \u003ccontainer parent=\"cid421005\" type=\"Folder\"\u003e1-7\u003c/container\u003e\n                            \u003cunitdate\u003e1939-1940\u003c/unitdate\u003e\n                        \u003c/did\u003e\n                    \u003c/c\u003e\n                    \u003cc id=\"ref98\" level=\"file\"\u003e\n                        \u003cdid\u003e\n                            \u003cunittitle\u003eSmall Photographs\u003c/unittitle\u003e\n                            \u003ccontainer id=\"cid422001\" type=\"Box\" label=\"Graphic materials\"\u003e10\u003c/container\u003e\n                            \u003ccontainer parent=\"cid422001\" type=\"Folder\"\u003e1-8\u003c/container\u003e\n                            \u003cunitdate\u003e1939-1940\u003c/unitdate\u003e\n                        \u003c/did\u003e\n                    \u003c/c\u003e\n                    \u003cc id=\"ref99\" level=\"file\"\u003e\n                        \u003cdid\u003e\n                            \u003cunittitle\u003eSmall Photographs\u003c/unittitle\u003e\n                            \u003ccontainer id=\"cid422002\" type=\"Box\" label=\"Graphic materials\"\u003e11\u003c/container\u003e\n                            \u003ccontainer parent=\"cid422002\" type=\"Folder\"\u003e1-7\u003c/container\u003e\n                            \u003cunitdate\u003e1939-1940\u003c/unitdate\u003e\n                        \u003c/did\u003e\n                    \u003c/c\u003e\n                    \u003cc id=\"ref100\" level=\"file\"\u003e\n                        \u003cdid\u003e\n                            \u003cunittitle\u003eSmall Photographs\u003c/unittitle\u003e\n                            \u003ccontainer id=\"cid422003\" type=\"Box\" label=\"Graphic materials\"\u003e12\u003c/container\u003e\n                            \u003ccontainer parent=\"cid422003\" type=\"Folder\"\u003e1-6\u003c/container\u003e\n                            \u003cunitdate\u003e1939-1940\u003c/unitdate\u003e\n                        \u003c/did\u003e\n                    \u003c/c\u003e\n                    \u003cc id=\"ref120\" level=\"file\"\u003e\n                        \u003cdid\u003e\n                            \u003cunittitle\u003eSmall - Color\u003c/unittitle\u003e\n                            \u003ccontainer id=\"cid447001\" type=\"Box\" label=\"Graphic materials\"\u003e12\u003c/container\u003e\n                            \u003ccontainer parent=\"cid447001\" type=\"Folder\"\u003e7\u003c/container\u003e\n                            \u003cunitdate\u003e1939-1940\u003c/unitdate\u003e\n                        \u003c/did\u003e\n                    \u003c/c\u003e\n                    \u003cc id=\"ref125\" level=\"file\"\u003e\n                        \u003cdid\u003e\n                            \u003cunittitle\u003eColor Positives\u003c/unittitle\u003e\n                            \u003ccontainer id=\"cid447002\" type=\"Box\" label=\"Graphic materials\"\u003e12\u003c/container\u003e\n                            \u003ccontainer parent=\"cid447002\" type=\"Folder\"\u003e8\u003c/container\u003e\n                            \u003cunitdate\u003e1939-1940\u003c/unitdate\u003e\n                        \u003c/did\u003e\n                    \u003c/c\u003e\n                \u003c/c\u003e\n                \u003cc id=\"ref141\" level=\"subseries\"\u003e\n                    \u003cdid\u003e\n                        \u003cunittitle\u003eSubseries VII. Photographs from other Institutions\u003c/unittitle\u003e\n                        \u003ccontainer id=\"cid437001\" type=\"Box\" label=\"Graphic materials\"\u003e13\u003c/container\u003e\n                        \u003ccontainer parent=\"cid437001\" type=\"Folder\"\u003e1-10\u003c/container\u003e\n                    \u003c/did\u003e\n                    \u003cscopecontent id=\"ref170\"\u003e\n                        \u003chead\u003eScope and Content\u003c/head\u003e\n                        \u003cp\u003eThis subseries contains a variety of photographs that Paul Gillespie obtained from the collections of other institutions.\u003c/p\u003e\n                    \u003c/scopecontent\u003e\n                    \u003cc id=\"ref196\" level=\"file\"\u003e\n                        \u003cdid\u003e\n                            \u003cunittitle\u003ePhotographs from other Institutions\u003c/unittitle\u003e\n                            \u003ccontainer id=\"cid451003\" type=\"Box\" label=\"Graphic materials\"\u003e13\u003c/container\u003e\n                            \u003ccontainer parent=\"cid451003\" type=\"Folder\"\u003e1-10\u003c/container\u003e\n                            \u003cunitdate normal=\"1939/1940\" type=\"inclusive\"\u003e1939-1940\u003c/unitdate\u003e\n                        \u003c/did\u003e\n                    \u003c/c\u003e\n                \u003c/c\u003e\n                \u003cc id=\"ref171\" level=\"subseries\"\u003e\n                    \u003cdid\u003e\n                        \u003cunittitle\u003eSubseries VIII. Other World Fairs\u003c/unittitle\u003e\n                    \u003c/did\u003e\n                    \u003cscopecontent id=\"ref180\"\u003e\n                        \u003chead\u003eScope and Content\u003c/head\u003e\n                        \u003cp\u003eThis subseries contains a small number of photographs that are from the 1964-65 New York World's Fair, the Golden Gate International Exposition or other world fairs. The photographs are a mixture of color or black \u0026amp; white, small and medium size prints.\u003c/p\u003e\n                    \u003c/scopecontent\u003e\n                    \u003cc id=\"ref197\" level=\"file\"\u003e\n                        \u003cdid\u003e\n                            \u003cunittitle\u003eOther World Fairs\u003c/unittitle\u003e\n                            \u003ccontainer id=\"cid451004\" type=\"Box\" label=\"Graphic materials\"\u003e13\u003c/container\u003e\n                            \u003ccontainer parent=\"cid451004\" type=\"Folder\"\u003e11\u003c/container\u003e\n                        \u003c/did\u003e\n                    \u003c/c\u003e\n                \u003c/c\u003e\n                \u003cc id=\"ref32\" level=\"subseries\"\u003e\n                    \u003cdid\u003e\n                        \u003cunittitle\u003eSubseries IX. Stereographs\u003c/unittitle\u003e\n                    \u003c/did\u003e\n                    \u003cscopecontent id=\"ref160\"\u003e\n                        \u003chead\u003eScope and Content\u003c/head\u003e\n                        \u003cp\u003eThis subseries contains several varieties of stereograph. One set is still housed in its original wooden box, along with an insert that reads, \"Stereo Pictures of The New York World Fair\" and \"Rogers and Rogers\" of Newark, NJ. Although this set appears to be commercially produced, the captions and numbering are handwritten. There are an additional 72 loose stereographs and a single \"Stereovue\" card that depicts 3 images.\u003c/p\u003e\n                    \u003c/scopecontent\u003e\n                    \u003cc id=\"ref198\" level=\"file\"\u003e\n                        \u003cdid\u003e\n                            \u003cunittitle\u003eStereographs\u003c/unittitle\u003e\n                            \u003ccontainer id=\"cid451005\" type=\"Box\" label=\"Graphic materials\"\u003e14-15\u003c/container\u003e\n                            \u003cunitdate\u003e1939-1940\u003c/unitdate\u003e\n                        \u003c/did\u003e\n                    \u003c/c\u003e\n                \u003c/c\u003e\n            \u003c/c\u003e\n            \u003cc id=\"ref34\" level=\"series\"\u003e\n                \u003cdid\u003e\n                    \u003cunittitle\u003eSeries II. Post Cards\u003c/unittitle\u003e\n                \u003c/did\u003e\n                \u003cscopecontent id=\"ref161\"\u003e\n                    \u003chead\u003eScope and Content\u003c/head\u003e\n                    \u003cp\u003eThis series contains approximately 200 picture postcards from the New York World Fair, the majority of which are unused souvenir cards. Five postcards are amateur photographic postcards.\u003c/p\u003e\n                \u003c/scopecontent\u003e\n                \u003cc id=\"ref199\" level=\"file\"\u003e\n                    \u003cdid\u003e\n                        \u003cunittitle\u003ePost Cards\u003c/unittitle\u003e\n                        \u003ccontainer id=\"cid451006\" type=\"Box\" label=\"Graphic materials\"\u003e15\u003c/container\u003e\n                        \u003cunitdate\u003e1939-1940\u003c/unitdate\u003e\n                    \u003c/did\u003e\n                \u003c/c\u003e\n            \u003c/c\u003e\n            \u003cc id=\"ref2\" level=\"series\"\u003e\n                \u003cdid\u003e\n                    \u003cunittitle\u003eSeries III. Scrap Books and Photo Albums\u003c/unittitle\u003e\n                \u003c/did\u003e\n                \u003cscopecontent id=\"ref162\"\u003e\n                    \u003chead\u003eScope and Content\u003c/head\u003e\n                    \u003cp\u003eThis series contains twelve photo albums and three scrap books of unknown origin that were collected by Paul Gillespie. Most of the albums and scrapbooks appear to have been created by different people who attended the New York World's Fair and contain a mix of amateur and souvenir photographs, memorabilia, newspaper clippings and some non-world's fair material. Of particular interest is a \"Diary and Scrap Book\" that includes diary style entries documenting a visitor's thirty-three separate visits to the fair over the course of its two seasons, as well as a collection of fair ephemera.\u003c/p\u003e\n                    \u003cp\u003eA series of photographs that were originally in vinyl sleeves and bound as an album, were rehoused in archival sleeves and are located in box 5, folders 6-8.\u003c/p\u003e\n                \u003c/scopecontent\u003e\n                \u003cc id=\"ref35\" level=\"item\"\u003e\n                    \u003cdid\u003e\n                        \u003cunittitle\u003ePhoto Album 1\u003c/unittitle\u003e\n                        \u003ccontainer id=\"cid451007\" type=\"Box\" label=\"Graphic materials\"\u003e16\u003c/container\u003e\n                    \u003c/did\u003e\n                \u003c/c\u003e\n                \u003cc id=\"ref36\" level=\"item\"\u003e\n                    \u003cdid\u003e\n                        \u003cunittitle\u003ePhoto Album 2\u003c/unittitle\u003e\n                        \u003ccontainer id=\"cid451008\" type=\"Box\" label=\"Graphic materials\"\u003e17\u003c/container\u003e\n                    \u003c/did\u003e\n                \u003c/c\u003e\n                \u003cc id=\"ref37\" level=\"item\"\u003e\n                    \u003cdid\u003e\n                        \u003cunittitle\u003ePhoto Albums 3-4\u003c/unittitle\u003e\n                        \u003ccontainer id=\"cid451009\" type=\"Box\" label=\"Graphic materials\"\u003e18\u003c/container\u003e\n                    \u003c/did\u003e\n                \u003c/c\u003e\n                \u003cc id=\"ref39\" level=\"item\"\u003e\n                    \u003cdid\u003e\n                        \u003cunittitle\u003ePhoto Albums 5-11\u003c/unittitle\u003e\n                        \u003ccontainer id=\"cid451010\" type=\"Box\" label=\"Graphic materials\"\u003e19\u003c/container\u003e\n                    \u003c/did\u003e\n                \u003c/c\u003e\n                \u003cc id=\"ref6\" level=\"item\"\u003e\n                    \u003cdid\u003e\n                        \u003cunittitle\u003eDiary and Scrap Book\u003c/unittitle\u003e\n                        \u003ccontainer id=\"cid451011\" type=\"Box\" label=\"Graphic materials\"\u003e19\u003c/container\u003e\n                    \u003c/did\u003e\n                \u003c/c\u003e\n                \u003cc id=\"ref3\" level=\"item\"\u003e\n                    \u003cdid\u003e\n                        \u003cunittitle\u003eScrap Books 1-2\u003c/unittitle\u003e\n                        \u003ccontainer id=\"cid412001\" type=\"Box\" label=\"Graphic materials\"\u003e20\u003c/container\u003e\n                    \u003c/did\u003e\n                \u003c/c\u003e\n            \u003c/c\u003e\n            \u003cc id=\"ref4\" level=\"series\"\u003e\n                \u003cdid\u003e\n                    \u003cunittitle\u003eSeries IV. Ephemera\u003c/unittitle\u003e\n                \u003c/did\u003e\n                \u003cscopecontent id=\"ref207\"\u003e\n                    \u003chead\u003eSee also\u003c/head\u003e\n                    \u003cp\u003eSeries VII. Oversize Materials\u003c/p\u003e\n                \u003c/scopecontent\u003e\n                \u003cscopecontent id=\"ref163\"\u003e\n                    \u003chead\u003eScope and Content\u003c/head\u003e\n                    \u003cp\u003eThis series contains a variety of ephemera and memorabilia from the New York World's Fair, including a large number of pamphlets, brochures and booklets from the fair's shows, corporate exhibits, and government pavilions. Of particular interest is a collection of menus from many of the fair's restaurants.\u003c/p\u003e\n                \u003c/scopecontent\u003e\n                \u003cc id=\"ref133\" level=\"file\"\u003e\n                    \u003cdid\u003e\n                        \u003cunittitle\u003eCorporations\u003c/unittitle\u003e\n                        \u003ccontainer id=\"cid451012\" type=\"Box\" label=\"Graphic materials\"\u003e21\u003c/container\u003e\n                        \u003ccontainer parent=\"cid451012\" type=\"Folder\"\u003e1-3\u003c/container\u003e\n                        \u003cunitdate normal=\"1939/1940\" type=\"inclusive\"\u003e1939-1940\u003c/unitdate\u003e\n                    \u003c/did\u003e\n                \u003c/c\u003e\n                \u003cc id=\"ref122\" level=\"file\"\u003e\n                    \u003cdid\u003e\n                        \u003cunittitle\u003eMenus\u003c/unittitle\u003e\n                        \u003ccontainer id=\"cid451013\" type=\"Box\" label=\"Graphic materials\"\u003e21\u003c/container\u003e\n                        \u003ccontainer parent=\"cid451013\" type=\"Folder\"\u003e4-5\u003c/container\u003e\n                        \u003cunitdate normal=\"1939/1940\" type=\"inclusive\"\u003e1939-1940\u003c/unitdate\u003e\n                    \u003c/did\u003e\n                \u003c/c\u003e\n                \u003cc id=\"ref123\" level=\"file\"\u003e\n                    \u003cdid\u003e\n                        \u003cunittitle\u003eNations\u003c/unittitle\u003e\n                        \u003ccontainer id=\"cid451016\" type=\"Box\" label=\"Graphic materials\"\u003e21\u003c/container\u003e\n                        \u003ccontainer parent=\"cid451016\" type=\"Folder\"\u003e6-7\u003c/container\u003e\n                        \u003cunitdate normal=\"1939/1940\" type=\"inclusive\"\u003e1939-1940\u003c/unitdate\u003e\n                    \u003c/did\u003e\n                \u003c/c\u003e\n                \u003cc id=\"ref202\" level=\"file\"\u003e\n                    \u003cdid\u003e\n                        \u003cunittitle\u003eNations\u003c/unittitle\u003e\n                        \u003ccontainer id=\"cid452001\" type=\"Box\" label=\"Graphic materials\"\u003e22\u003c/container\u003e\n                        \u003ccontainer parent=\"cid452001\" type=\"Folder\"\u003e1-2\u003c/container\u003e\n                        \u003cunitdate\u003e1939-1940\u003c/unitdate\u003e\n                    \u003c/did\u003e\n                \u003c/c\u003e\n                \u003cc id=\"ref134\" level=\"file\"\u003e\n                    \u003cdid\u003e\n                        \u003cunittitle\u003eU.S. Cities and States\u003c/unittitle\u003e\n                        \u003ccontainer id=\"cid451017\" type=\"Box\" label=\"Graphic materials\"\u003e22\u003c/container\u003e\n                        \u003ccontainer parent=\"cid451017\" type=\"Folder\"\u003e3\u003c/container\u003e\n                        \u003cunitdate normal=\"1939/1940\" type=\"inclusive\"\u003e1939-1940\u003c/unitdate\u003e\n                    \u003c/did\u003e\n                \u003c/c\u003e\n                \u003cc id=\"ref137\" level=\"file\"\u003e\n                    \u003cdid\u003e\n                        \u003cunittitle\u003eMiscellaneous\u003c/unittitle\u003e\n                        \u003ccontainer id=\"cid451014\" type=\"Box\" label=\"Graphic materials\"\u003e22\u003c/container\u003e\n                        \u003ccontainer parent=\"cid451014\" type=\"Folder\"\u003e4-6\u003c/container\u003e\n                        \u003cunitdate normal=\"1939/1940\" type=\"inclusive\"\u003e1939-1940\u003c/unitdate\u003e\n                    \u003c/did\u003e\n                \u003c/c\u003e\n            \u003c/c\u003e\n            \u003cc id=\"ref140\" level=\"series\"\u003e\n                \u003cdid\u003e\n                    \u003cunittitle\u003eSeries V. Correspondence and Notebooks\u003c/unittitle\u003e\n                \u003c/did\u003e\n                \u003cscopecontent id=\"ref164\"\u003e\n                    \u003chead\u003eScope and Content\u003c/head\u003e\n                    \u003cp\u003eThis series contains two notebooks, one piece of correspondence and some associated ephemera. The notebooks mostly contain handwritten records of Mr. Gillespie's collection activities and chronological notes on daily World's Fair events. The notebooks also contain a variety of loose ephemera from his research activities. The correspondence documents the results of a 2010 auction of some of Mr. Gillespie's World Fair collection. It is unclear how much or how often Mr. Gillespie sought to sell parts of his collection.\u003c/p\u003e\n                \u003c/scopecontent\u003e\n                \u003cc id=\"ref201\" level=\"file\"\u003e\n                    \u003cdid\u003e\n                        \u003cunittitle\u003eCorrespondence and Notebooks\u003c/unittitle\u003e\n                        \u003ccontainer id=\"cid451018\" type=\"Box\" label=\"Text\"\u003e22\u003c/container\u003e\n                        \u003ccontainer parent=\"cid451018\" type=\"Folder\"\u003e7\u003c/container\u003e\n                        \u003cunitdate\u003e2010\u003c/unitdate\u003e\n                    \u003c/did\u003e\n                \u003c/c\u003e\n            \u003c/c\u003e\n            \u003cc id=\"ref150\" level=\"series\"\u003e\n                \u003cdid\u003e\n                    \u003cunittitle\u003eSeries VI. Publications\u003c/unittitle\u003e\n                \u003c/did\u003e\n                \u003cscopecontent id=\"ref208\"\u003e\n                    \u003chead\u003eSee also\u003c/head\u003e\n                    \u003cp\u003eSeries VII. Oversize Materials\u003c/p\u003e\n                \u003c/scopecontent\u003e\n                \u003cscopecontent id=\"ref165\"\u003e\n                    \u003chead\u003eScope and Content\u003c/head\u003e\n                    \u003cp\u003eThis series contains a wide variety of books and periodicals that cover an assortment of world fair related topics. Many items deal exclusively with the 1939-40 New York World's Fair, but others either survey world fairs generally or relate to a different fair entirely.\u003c/p\u003e\n                \u003c/scopecontent\u003e\n                \u003cc id=\"ref175\" level=\"file\"\u003e\n                    \u003cdid\u003e\n                        \u003cunittitle\u003eNew York World's Fair Corporation\u003c/unittitle\u003e\n                        \u003ccontainer id=\"cid452003\" type=\"Box\" label=\"Books\"\u003e23\u003c/container\u003e\n                        \u003ccontainer parent=\"cid452003\" type=\"Folder\"\u003e1-2\u003c/container\u003e\n                        \u003cunitdate\u003e1939,1941\u003c/unitdate\u003e\n                    \u003c/did\u003e\n                \u003c/c\u003e\n                \u003cc id=\"ref185\" level=\"file\"\u003e\n                    \u003cdid\u003e\n                        \u003cunittitle\u003eCity of New York\u003c/unittitle\u003e\n                        \u003ccontainer id=\"cid452004\" type=\"Box\" label=\"Books\"\u003e23\u003c/container\u003e\n                        \u003ccontainer parent=\"cid452004\" type=\"Folder\"\u003e3\u003c/container\u003e\n                        \u003cunitdate\u003e1939\u003c/unitdate\u003e\n                    \u003c/did\u003e\n                \u003c/c\u003e\n                \u003cc id=\"ref174\" level=\"file\"\u003e\n                    \u003cdid\u003e\n                        \u003cunittitle\u003eMuseum Exhibit Books\u003c/unittitle\u003e\n                        \u003ccontainer id=\"cid452005\" type=\"Box\" label=\"Books\"\u003e23\u003c/container\u003e\n                        \u003ccontainer parent=\"cid452005\" type=\"Folder\"\u003e4\u003c/container\u003e\n                        \u003cunitdate\u003e1980, 1984, 1990\u003c/unitdate\u003e\n                    \u003c/did\u003e\n                \u003c/c\u003e\n                \u003cc id=\"ref176\" level=\"file\"\u003e\n                    \u003cdid\u003e\n                        \u003cunittitle\u003ePeriodicals\u003c/unittitle\u003e\n                        \u003ccontainer id=\"cid452006\" type=\"Box\" label=\"Books\"\u003e23\u003c/container\u003e\n                        \u003ccontainer parent=\"cid452006\" type=\"Folder\"\u003e5-7\u003c/container\u003e\n                        \u003cunitdate normal=\"1938/1940\" type=\"inclusive\"\u003e1938-1940\u003c/unitdate\u003e\n                    \u003c/did\u003e\n                \u003c/c\u003e\n                \u003cc id=\"ref178\" level=\"file\"\u003e\n                    \u003cdid\u003e\n                        \u003cunittitle\u003ePicture Books\u003c/unittitle\u003e\n                        \u003ccontainer id=\"cid452007\" type=\"Box\" label=\"Books\"\u003e24\u003c/container\u003e\n                        \u003ccontainer parent=\"cid452007\" type=\"Folder\"\u003e1-2\u003c/container\u003e\n                        \u003cunitdate\u003e1977, 2002\u003c/unitdate\u003e\n                    \u003c/did\u003e\n                \u003c/c\u003e\n                \u003cc id=\"ref177\" level=\"file\"\u003e\n                    \u003cdid\u003e\n                        \u003cunittitle\u003eSouvenir Books\u003c/unittitle\u003e\n                        \u003ccontainer id=\"cid452008\" type=\"Box\" label=\"Books\"\u003e24\u003c/container\u003e\n                        \u003ccontainer parent=\"cid452008\" type=\"Folder\"\u003e3-4\u003c/container\u003e\n                        \u003cunitdate\u003e1939-1940, 1973\u003c/unitdate\u003e\n                    \u003c/did\u003e\n                \u003c/c\u003e\n                \u003cc id=\"ref173\" level=\"file\"\u003e\n                    \u003cdid\u003e\n                        \u003cunittitle\u003eOther World Fairs\u003c/unittitle\u003e\n                        \u003ccontainer id=\"cid452009\" type=\"Box\" label=\"Books\"\u003e24\u003c/container\u003e\n                        \u003ccontainer parent=\"cid452009\" type=\"Folder\"\u003e5-7\u003c/container\u003e\n                        \u003cunitdate\u003e1901, 1932, 1964-1965, 1985\u003c/unitdate\u003e\n                    \u003c/did\u003e\n                \u003c/c\u003e\n                \u003cc id=\"ref179\" level=\"file\"\u003e\n                    \u003cdid\u003e\n                        \u003cunittitle\u003eMisscellaneous and Oversize Books\u003c/unittitle\u003e\n                        \u003ccontainer id=\"cid452010\" type=\"Box\" label=\"Books\"\u003e25\u003c/container\u003e\n                        \u003cunitdate\u003e1893-1894, 1941, 1962, 1966, 1978, 1981, 1985-1986, 1988-1989, 1995, 1999\u003c/unitdate\u003e\n                    \u003c/did\u003e\n                \u003c/c\u003e\n            \u003c/c\u003e\n            \u003cc id=\"ref192\" level=\"series\"\u003e\n                \u003cdid\u003e\n                    \u003cunittitle\u003eSeries VII. Oversize Materials\u003c/unittitle\u003e\n                    \u003cunitdate normal=\"1939/1989\" type=\"inclusive\"\u003e1939, 1986, 1989\u003c/unitdate\u003e\n                \u003c/did\u003e\n                \u003cscopecontent id=\"ref193\"\u003e\n                    \u003chead\u003eScoep and Content\u003c/head\u003e\n                    \u003cp\u003eThis series includes oversize materials from Series I. Photographs; Series V. Ephemera; and Series VI. Publications.\u003c/p\u003e\n                    \u003cp\u003eNoteworthy items include, \"Time Tears On,\" a souvenir book made for and by New York World's Fair employees, and the \"U.S. Camera, World's Fair Issue,\" which contains an interesting collection of fair photography.\u003c/p\u003e\n                \u003c/scopecontent\u003e\n                \u003cc id=\"ref203\" level=\"file\"\u003e\n                    \u003cdid\u003e\n                        \u003cunittitle\u003eOversize Materials\u003c/unittitle\u003e\n                        \u003ccontainer id=\"cid452011\" type=\"Box\" label=\"Mixed materials\"\u003e26\u003c/container\u003e\n                    \u003c/did\u003e\n                \u003c/c\u003e\n            \u003c/c\u003e\n        "
        }
    }
}